{
  "metadata": {
    "file_path": "db\\A7614095-C9D7-4C82-8BBC-8DB7279DFB60\\2022-495-sayili-genelyazi.html",
    "title": "2022-495 sayılı genelyazı",
    "description": "Ankara, 31.12.2022 Mali Danışmanlık-290-58377 Özü: Vergi Usul Kanunu ve Gelir Vergisi Kanununda yer alan ve 2023 Yılında uygulanacak olan bazı maktu had ve miktarlar hk.",
    "keywords": [],
    "author": "",
    "created_date": "",
    "last_modified": "",
    "language": "tr",
    "encoding": "utf-8"
  },
  "content": {
    "text": "﻿ 2022-495 sayılı genelyazı Email Gönder 2022-495 sayılı genelyazı << Fihrist-Ana sayfa >> 2022-495 sayılı genelyazı NOTERLİK MEVZUATI DİZİNİ    NOTERLİK İŞLEMLERİ DİZİNİ GENELGELER GENEL YAZILAR    48 SAYILI GENELGE Ankara, 31.12.2022 Mali Danışmanlık-290-58377 Özü: Vergi Usul Kanunu ve Gelir Vergisi Kanununda yer alan ve 2023 Yılında uygulanacak olan bazı maktu had ve miktarlar hk. ............. NOTER ODASI BAŞKANLIĞINA ............. NOTERLİĞİNE Hazine ve Maliye Bakanlığınca hazırlanan ve Resmi Gazete’nin 30 Aralık 2022 günlü ve 32059 (2. Mükerrer) nüshasında yayımlanan 1- 544. Sıra No.lu Vergi Usul Kanunu Genel Tebliği, 2- 322 ve 323.Seri No.lu Gelir Vergisi Kanunu Genel Tebliğleri, Yayımlanmış ve bu Tebliğlerde 01.01.2023 tarihinden itibaren uygulanacak olan bazı maktu had ve miktarlar yeniden tespit edilmiş bulunmaktadır. Sözü edilen Tebliğlerin noterlikleri ilgilendiren bölümleri aşağıda belirtilmiştir Bilgi edinilmesini rica ederim. Emine ÇAĞLAYAN Başkan GENELYAZI:( 495) VERGİ USUL KANUNU GENEL TEBLİĞİ (SIRA NO: 544) Amaç MADDE 1 – (1) Bu Tebliğin amacı, 4/1/1961 tarihli ve 213 sayılı Vergi Usul Kanununun 104, mükerrer 115, 153/A, 177, 232, 252, mükerrer 257, 313, 323, 343, 352 (Kanuna Bağlı Cetvel), 353, 355, mükerrer 355, 370, EK 1 ve EK 11 inci maddelerinde yer alıp 2021 yılında uygulanan had ve tutarların yeniden değerleme oranında artırılması suretiyle 1/1/2023 tarihi itibarıyla uygulanacak had ve tutarların belirlenmesine ilişkin hususların açıklanmasıdır. Yasal düzenlemeler MADDE 2 – (1) 213 sayılı Kanunun mükerrer 414 üncü maddesinin üçüncü fıkrasında, “Bu Kanunda yer alan maktu hadler ile asgari ve azami miktarları belirtilmiş olan para ile ödenecek ceza miktarları, her yıl bir önceki yıla ilişkin olarak bu Kanun uyarınca belirlenen yeniden değerleme oranında artırılmak suretiyle uygulanır. Bu şekilde hesaplanan maktu had ve miktarların yüzde beşini aşmayan kesirler dikkate alınmaz. Cumhurbaşkanı, bu suretle tespit edilen had ve miktarları yarısına kadar artırmaya veya indirmeye, nispi hadleri ise iki katına kadar artırmaya veya yarısına kadar indirmeye veya tekrar kanuni seviyesine getirmeye yetkilidir.” hükmü yer almaktadır. Yeniden değerleme oranında artırılan had ve tutarlar MADDE 3 – (1) 213 sayılı Kanunun mükerrer 414 üncü maddesi ile mezkur Kanunun 104 üncü maddesinin üçüncü fıkrası hükmü uyarınca aynı Kanunun 104, mükerrer 115, 153/A, 177, 232, 252, mükerrer 257, 313, 323, 343, 352 (Kanuna Bağlı Cetvel), 353, 355, mükerrer 355, 370, EK 1 ve EK 11 inci maddelerinde yer alıp 2022 yılında uygulanan had ve tutarların, 2022 yılı için %122,93 (yüz yirmi iki virgül doksan üç) olarak tespit edilen yeniden değerleme oranında artırılması, artırılan bu had ve tutarların Kanunun 104 üncü maddesinin birinci fıkrasının (4 numaralı) bendinde yer alan tutarın mezkur yetkiye istinaden yeniden artırılması suretiyle belirlenen ve 1/1/2023 tarihinden itibaren uygulanacak olan had ve tutarlar ekli listede gösterilmiştir. Yürürlük MADDE 4 – (1) Bu Tebliğ 1/1/2023 tarihinde yürürlüğe girer. Yürütme MADDE 5 – (1) Bu Tebliğ hükümlerini Hazine ve Maliye Bakanı yürütür. VERGİ USUL KANUNUNDA YER ALAN VE 01/01/2023 TARİHİNDEN GEÇERLİ OLMAK ÜZERE UYGULANACAK OLAN HAD VE MİKTARLAR MADDE NO KONUSU 2023 Yılında Uygulanacak Miktar (TL) MADDE 177- Bilanço hesabı esasına göre defter tutma hadleri 1- Yıllık; - Alış tutarı - Satış tutarı 890.000 1.270.000 2- Yıllık gayrisafi iş hasılatı 440.000 3- İş hasılatının beş katı ile yıllık satış tutarının toplamı 890.000 MADDE 232- Fatura kullanma mecburiyeti 4.400 MADDE 313- Doğrudan gider yazılacak demirbaş ve peştemallıklar 4.400 MADDE 343- En az ceza haddi - Damga vergisinde - Diğer vergilerde 55 110 MADDE 352- Usulsüzlük dereceleri ve cezaları (Kanuna bağlı cetvel) I inci derece usulsüzlükler 2- Sermaye şirketi dışında kalan birinci sınıf tüccarlar ve serbest meslek erbabı 420 II nci derece usulsüzlükler 2- Sermaye şirketi dışında kalan birinci sınıf tüccarlar ve serbest meslek erbabı 210 MADDE 353- Fatura ve benzeri evrak verilmemesi ve alınmaması ile diğer şekil ve usul hükümlerine uyulmaması 1- Elektronik belge olarak düzenlenmesi gerekenler dahil olmak üzere fatura, gider pusulası, müstahsil makbuzu, serbest meslek makbuzu verilmemesi, alınmaması - Bir takvim yılı içinde her bir belge nevine ilişkin olarak kesilecek toplam ceza 2.200 1.100.000 4- Hazine ve Maliye Bakanlığınca tutulma ve günü gününe kayıt edilme mecburiyeti getirilen defterlerin; bulundurulmaması, günü gününe kayıt yapılmaması, yetkililere ibraz edilmemesi ile levha bulundurma ve asma mecburiyetine uyulmaması 1.100 6- Belirlenen muhasebe standartlarına, tek düzen hesap planına ve mali tablolara ilişkin usul ve esaslar ile muhasebeye yönelik bilgisayar programlarının üretilmesine ilişkin kural ve standartlara uymayanlara 26.000 7- Kamu kurum ve kuruluşları ile gerçek ve tüzel kişilerce yapılacak işlemlerde kullanılma zorunluluğu getirilen vergi numarasını kullanmaksızın işlem yapanlara 1.300 9- 4358 sayılı Kanun uyarınca vergi kimlik numarası kullanma zorunluluğu getirilen kuruluşlardan yaptıkları işlemlere ilişkin bildirimleri, belirlenen standartlarda ve zamanda yerine getirmeyenlere 5.500 MADDE 355 b) Damga vergisinde -Her bir kağıt için kesilecek özel usulsüzlük cezası (En az) 9 MÜKERRER MADDE 355- Bilgi vermekten çekinenler ile 107/A, mükerrer 242, 256, 257 ve mükerrer 257 ci madde hükmüne uymayanlar için ceza 1-Birinci sınıf tüccarlar ile serbest meslek erbabı hakkında 7.500 Elektronik tebligat adresi alma mecburiyetine uymayanlar için -Birinci sınıf tüccarlar ile serbest meslek erbabı hakkında 4.400 Tahsilat ve ödemelerini banka, benzeri finans kurumları veya posta idarelerince düzenlenen belgelerle tevsik etme zorunluluğuna uymayanlara bir takvim yılı içinde kesilecek toplam özel usulsüzlük cezası 5.500.000 GELİR VERGİSİ GENEL TEBLİĞİ (SERİ NO: 322) BİRİNCİ BÖLÜM Amaç ve Kapsam Amaç ve kapsam MADDE 1- (1) Bu Tebliğin amacı; 31/12/1960 tarihli ve 193 sayılı Gelir Vergisi Kanununda 3/11/2022 tarihli ve 7420 sayılı Gelir Vergisi Kanunu ile Bazı Kanun ve Kanun Hükmünde Kararnamelerde Değişiklik Yapılmasına Dair Kanunla yapılan değişiklikler ile aynı Kanunun geçici 1 inci maddesinin uygulamasına ilişkin usul ve esasları düzenlemektir. …. DÖRDÜNCÜ BÖLÜM Elektrik, Doğalgaz ve Benzeri Isınma Giderleri Karşılığı Olarak Çalışanlara Yapılan Ödemelerde Gelir Vergisi İstisnası Yasal düzenleme MADDE 7- (1) 7420 sayılı Kanunun geçici1 inci maddesinde, “(1) Bu maddenin yürürlüğe girdiği tarihten itibaren işverenler tarafından çalışanlara elektrik, doğalgaz ve diğer ısınma giderlerine karşılık olmak üzere 30/6/2023 tarihine kadar (bu tarih dâhil) mevcut ücretlerine/prime esas kazançlarına ilave olarak yapılan aylık 1.000 Türk lirasını aşmayan ödemeler, 31/5/2006 tarihlive 5510 sayılı Sosyal Sigortalar ve Genel Sağlık Sigortası Kanununa göre prime esas kazanca dâhil edilmez ve bu tutar üzerinden 31/12/1960 tarihli ve 193 sayılı Gelir Vergisi Kanunu uyarınca gelir vergisi hesaplanmaz. (2) Bu maddenin uygulanmasına ilişkin usul ve esasları belirlemeye ilgisine göre Hazine ve Maliye Bakanlığı ve Çalışma ve Sosyal Güvenlik Bakanlığı yetkilidir.” hükmü yer almaktadır. İstisnanın kapsamı ve şartları MADDE 8- (1) 193 sayılı Kanunun 61 inci maddesinde, ücret, işverene tabi ve belirli bir işyerine bağlı olarak çalışanlara hizmet karşılığı verilen para ve ayınlar ile sağlanan ve parayla temsil edilebilen menfaatler olarak tanımlanmış olup ücretin; ödenek, tazminat, kasa tazminatı (mali sorumluluk tazminatı), tahsisat, zam, avans, aidat, huzur hakkı, prim, ikramiye, gider karşılığı veya başka adlar altında ödenmiş olması veya bir ortaklık münasebeti niteliğinde olmamak şartı ile kazancın belli bir yüzdesi şeklinde tayin edilmiş bulunmasının onun mahiyetini değiştirmeyeceği  belirtilmiştir. Dolayısıyla hizmet erbabına ödenen aylık ücret, mesai, prim, ikramiye, gider karşılığı ve sair adlarla yapılan tüm ödemeler ve sağlanan menfaatler de ücret kapsamında değerlendirilmektedir. (2) İşverenler tarafından maddenin yürürlüğe girdiği 9/11/2022 tarihinden 30/6/2023 tarihine kadar (bu tarih dahil) çalışanlara mevcut ücretlerine ilave olarak elektrik, doğalgaz ve diğer ısınma giderlerine karşılık olmak üzere toplam aylık tutarı 1.000 Türk lirasını aşmayan ödemeler gelir vergisinden istisna edilmiştir. (3) İşverenler tarafından hizmet erbabına bu şekilde yapılan ödemelerin istisna kapsamında değerlendirilebilmesi için söz konusu ödemelerin; a) 9/11/2022 tarihi ila 30/6/2023 tarihi (bu tarih dahil) arasında yapılması, b) Elektrik, doğalgaz ve diğer ısınma giderlerine karşılık olmak üzere yapılması, c) Aylık 1.000 Türk lirasını aşmaması, d) Mevcut ücretlerine ilave olarak yapılması gerekmektedir şarttır … (9) Bu kapsamda yapılan ödemelere ilişkin olarak damga vergisi istisnası bulunmamaktadır. ………. GELİR VERGİSİ GENEL TEBLİĞİ (SERİ NO: 323.) BİRİNCİ BÖLÜM Amaç ve Yasal Düzenlemeler Amaç MADDE 1 – (1) Bu Tebliğin amacı, 31/12/1960 tarihli ve 193 sayılı Gelir Vergisi Kanununun 9/10, 21, 23/8, 23/10, 31, 40/1, 40/7, 47, 48, 68 mükerrer 80, 82, 86, 103 ve mükerrer 121 inci maddelerinde yer alan ve yeniden değerleme oranında artırılan maktu had ve tutarlar, basit usule tabi mükelleflerde toplu belge düzenleme uygulaması ile 1/1/2006 tarihinden önce ihraç edilen bir kısım menkul kıymetlerden 2022 takvim yılında elde edilen menkul sermaye iradının beyanında dikkate alınacak indirim oranı uygulamasına ilişkin hususların açıklanmasıdır. Yasal düzenlemeler MADDE 2 – (1) 193 sayılı Kanunun mükerrer 121 inci maddesinde: “… Birinci fıkrada yer alan tutar, her yıl bir önceki yıla ilişkin olarak 213 sayılı Vergi Usul Kanunu hükümlerine göre belirlenen yeniden değerleme oranında artırılmak suretiyle uygulanır. Bu şekilde hesaplanan tutarın % 5'ini aşmayan kesirler dikkate alınmaz. Cumhurbaşkanı, birinci fıkrada yer alan oranı ve tutarı iki katına kadar artırmaya, sıfıra kadar indirmeye, kanuni oran ve tutarına getirmeye; Maliye Bakanlığı, maddenin uygulanmasına ilişkin usul ve esasları belirlemeye yetkilidir.” hükmü yer almaktadır. (2) 193 sayılı Kanunun mükerrer 123 üncü maddesinde: “… 2.Bu Kanunun 9/10, 19, 21, 23/8, 23/10, 31, 40/1, 40/7, 47, 48, 68 mükerrer 80, 82 ve 86 ncı maddeleri ile 89 uncu maddesinin birinci fıkrasının (15) numaralı bendinde yer alan maktu had ve tutarlar, her yıl bir önceki yıla ilişkin olarak Vergi Usul Kanunu hükümlerine göre belirlenen yeniden değerleme oranında artırılmak suretiyle uygulanır. Bu şekilde hesaplanan maktu had ve tutarların % 5'ini aşmayan kesirler dikkate alınmaz. Cumhurbaşkanı, bu surette tespit edilen had ve tutarları % 50'sine kadar artırmaya veya indirmeye yetkilidir.3.Bu Kanunun 103 üncü maddesinde yer alan vergi tarifesinin gelir dilim tutarları hakkında, bu maddenin (2) numaralı fıkrası uygulanır.”hükmü yer almaktadır. İKİNCİ BÖLÜM Yeniden Değerleme Oranında Artırılan Had ve Tutarlar Yeniden değerleme oranında artırılan had ve tutarlar MADDE 3 – (1) 193 sayılı Kanunun mükerrer 123 üncü maddesi hükmü uyarınca, aynı Kanunun 9/10, 21, 23/8, 23/10, 31, 40/1, 40/7, 47, 48, 68 mükerrer 80, 82, 86, ve 103 üncü maddelerinde yer alan ve 2022 yılında uygulanan had ve tutarlar 24/11/2022 tarihli ve 32023 sayılı Resmî Gazete’de yayımlanan Vergi Usul Kanunu Genel Tebliği (Sıra No:542) ile 2022 yılı için % 122,93 (yüz yirmi iki virgül doksan üç) olarak tespit edilen yeniden değerleme oranında artırılması suretiyle belirlenerek, 2023 takvim yılında uygulanacak olan had ve tutarlar aşağıdaki şekilde tespit edilmiştir. Yemek bedelinde istisna tutarı İşyerinde veya müştemilatında yemek verilmeyen durumlarda çalışılan günlere ait bir günlük yemek bedeline ilişkin istisna tutarı 110 TL İşverenler tarafından hizmet erbabına işyerinde veya müştemilatında yemek verilmeyen durumlarda, yemek bedelinin nakit olarak verilmesi suretiyle sağlanan menfaatler de istisna kapsamına alınmıştır. Hizmet erbabına nakit olarak ödenen yemek bedelinin gelir vergisinden istisna edilebilmesi için; a) İşverenler tarafından işyerinde veya müştemilatında yemek verilmemesi, b) Günlük yemek bedelinin 110 Türk lirasını aşmaması, c) Fiilen çalışılan günlere ilişkin olması, gerekmektedir. Nakit olarak yapılan yemek bedeli ödemelerinin, 18/11/2008 tarihli ve 27058 sayılı Resmî Gazete’de yayımlanan Ücret, Prim, İkramiye ve Bu Nitelikteki Her Türlü İstihkakın Bankalar Aracılığıyla Ödenmesine Dair Yönetmelikte belirlenen ödeme usulüne göre yapılması gerekmektedir. İşverenler tarafından hizmet erbabına yapılan ödemelere ilişkin olarak düzenlenen kağıtlarda yer alan tutarın, 193 sayılı Kanunun 23 üncü maddesinin birinci fıkrasının (19) numaralı bendinde yer alan istisnaya isabet eden kısmı damga vergisinden istisnadır. Ulaşım gideri istisna tutarı 193 sayılı Kanun 23 üncü maddesinin birinci fıkrasının (10) numaralı bendinde yer alan işverenlerce hizmet erbabının işyerine gidip gelmesi için sağlanan menfaatlere ilişkin istisna tutarı 56 TL Engellilik indirim tutarları 193 sayılı Kanunun 31 inci maddesinin ikinci fıkrasında yer alan engellilik indirimi tutarları; - Birinci derece engelliler için             4.400. TL, - İkinci derece engelliler için             2.600 TL, - Üçüncü derece engelliler için          1.100 TL, ……. Demirbaşa kaydedilmek üzere otomobil alımında amortisman ve gider uygulama sınırı 193 sayılı Gelir Vergisi Kanunun mesleki giderlere dair 68 inci maddesinin birinci fıkrasının; - 4 numaralı bendinde araç amortismanı olarak indirim konusu yapılabilecek tutar; özel tüketim vergisi ve katma değer vergisi hariç 500.000 TL, vergilerin maliyet bedeline eklendiği veya binek otomobilin ikinci el olarak iktisap edildiği hallerde 950.000 TL, - 5 numaralı bendinde gider olarak indirim konusu yapılabilecek aylık araç kiralama bedeli 17.000 TL, indirim konusu yapılabilecek özel tüketim vergisi ve katma değer vergisinin toplam tutarı 440.000 TL, olarak tespit edilmiştir. 2023 yılı gelirlerinin vergilendirilmesinde vergi matrah dilim ve nispetleri 193 sayılı Kanunun 103 üncü maddesinin birinci fıkrasında yer alan gelir vergisine tabi gelirlerin vergilendirilmesinde esas alınan tarife, 2023 takvim yılı gelirlerinin vergilendirilmesinde esas alınmak üzere aşağıdaki şekilde yeniden belirlenmiştir. 70.000 TL'ye kadar                                                                                                   % 15 150.000 TL'nin 70.000 TL'si için 10.500 TL, fazlası                                                       % 20 370.000 TL'nin 150.000 TL'si için 26.500 TL, (ücret gelirlerinde 550.000 TL'nin 150.000 TL'si için 26.500 TL), fazlası                                                                % 27 1.900.000 TL'nin 370.000 TL'si için 85.900 TL, (ücret gelirlerinde 1.900.000 TL'nin 550.000 TL'si için 134.500 TL), fazlası                                    % 35 1.900.000 TL’den fazlasının 1.900.000 TL’si için 621.400 TL (ücret gelirlerinde 1.900.000 TL’den fazlasının 1.900.000 TL’si için 607.000TL), fazlası                   % 40 Güncelleme: 07.01.2023 © Noterlik Rehberi (Sait Doğan - Sakarya 5. Noteri)",
    "headings": [
      {
        "level": 1,
        "text": "2022-495 sayılı genelyazı",
        "id": "",
        "class": [
          "p_Heading1"
        ]
      }
    ],
    "links": [
      {
        "text": "",
        "href": "https://twitter.com/share",
        "title": "",
        "target": "",
        "type": "external"
      },
      {
        "text": "Email Gönder",
        "href": "mailto:?body=noterlikrehberi.net/rehber/index.html%3F2022-495-sayili-genelyazi.html",
        "title": "",
        "target": "",
        "type": "internal"
      },
      {
        "text": "2022-495 sayılı genelyazı",
        "href": "#",
        "title": "",
        "target": "",
        "type": "anchor"
      },
      {
        "text": "<< Fihrist-Ana sayfa >>",
        "href": "index.html?2022-495-sayili-genelyazi.html",
        "title": "",
        "target": "_top",
        "type": "internal"
      },
      {
        "text": "NOTERLİK MEVZUATI DİZİNİ",
        "href": "javascript:void(0);",
        "title": "NOTERLİK MEVZUATI DİZİNİ",
        "target": "",
        "type": "internal"
      },
      {
        "text": "NOTERLİK İŞLEMLERİ DİZİNİ",
        "href": "javascript:void(0);",
        "title": "NOTERLİK İŞLEMLERİ DİZİNİ",
        "target": "",
        "type": "internal"
      },
      {
        "text": "GENELGELER GENEL YAZILAR",
        "href": "javascript:void(0);",
        "title": "NOTERLİK HAK.TÜM GENELGELER GENEL YAZILAR",
        "target": "",
        "type": "internal"
      },
      {
        "text": "48 SAYILI GENELGE",
        "href": "ortak-cari-hesap-islemleri-hak-birlestirilmis-48-sayili-genelge.html",
        "title": "ORTAK CARİ HESAP İŞLELERİ HAK. BİRLEŞTİRİLMİŞ 48 SAYILI GENELGE",
        "target": "",
        "type": "internal"
      },
      {
        "text": "Resmi Gazete’nin 30 Aralık 2022 günlü ve 32059 (2. Mükerrer) nüshasında yayımlanan",
        "href": "https://www.resmigazete.gov.tr/fihrist?tarih=2022-12-30&mukerrer=2",
        "title": "",
        "target": "_blank",
        "type": "external"
      },
      {
        "text": "544. Sıra No.lu Vergi Usul Kanunu Genel Tebliği,",
        "href": "https://www.resmigazete.gov.tr/eskiler/2022/12/20221230M2-15.htm",
        "title": "",
        "target": "_blank",
        "type": "external"
      },
      {
        "text": "322",
        "href": "https://www.resmigazete.gov.tr/eskiler/2022/12/20221230M2-12.htm",
        "title": "",
        "target": "_blank",
        "type": "external"
      },
      {
        "text": "323.Seri No.lu Gelir Vergisi Kanunu Genel Tebliğleri",
        "href": "https://www.resmigazete.gov.tr/eskiler/2022/12/20221230M2-13.htm",
        "title": "",
        "target": "_blank",
        "type": "external"
      },
      {
        "text": "Güncelleme: 07.01.2023",
        "href": "hangi-konular-guncellendi.html",
        "title": "",
        "target": "hmcontent",
        "type": "internal"
      },
      {
        "text": "© Noterlik Rehberi (Sait Doğan - Sakarya 5. Noteri)",
        "href": "fihrist.html",
        "title": "",
        "target": "hmcontent",
        "type": "internal"
      }
    ],
    "images": [
      {
        "src": "contents_off.png",
        "alt": "",
        "title": "",
        "width": "",
        "height": ""
      }
    ],
    "tables": [
      {
        "headers": [],
        "rows": [
          [
            "MADDE NO",
            "KONUSU",
            "2023 Yılında\nUygulanacak Miktar (TL)"
          ],
          [
            "MADDE 177-",
            "Bilanço hesabı esasına göre defter tutma hadleri",
            ""
          ],
          [
            "",
            "1- Yıllık;\n - Alış tutarı\n- Satış tutarı",
            "890.000\n1.270.000"
          ],
          [
            "",
            "2- Yıllık gayrisafi iş hasılatı",
            "440.000"
          ],
          [
            "",
            "3- İş hasılatının beş katı ile yıllık satış tutarının toplamı",
            "890.000"
          ],
          [
            "MADDE 232-",
            "Fatura kullanma mecburiyeti",
            "4.400"
          ],
          [
            "MADDE 313-",
            "Doğrudan gider yazılacak demirbaş ve peştemallıklar",
            "4.400"
          ],
          [
            "MADDE 343-",
            "En az ceza haddi",
            ""
          ],
          [
            "",
            "- Damga vergisinde\n- Diğer vergilerde",
            "55\n110"
          ],
          [
            "MADDE 352-",
            "Usulsüzlük dereceleri ve cezaları\n(Kanuna bağlı cetvel)",
            ""
          ],
          [
            "",
            "I inci derece usulsüzlükler",
            ""
          ],
          [
            "",
            "2- Sermaye şirketi dışında kalan birinci sınıf tüccarlar ve serbest meslek erbabı",
            "420"
          ],
          [
            "",
            "II nci derece usulsüzlükler",
            ""
          ],
          [
            "",
            "2- Sermaye şirketi dışında kalan birinci sınıf tüccarlar ve serbest meslek erbabı",
            "210"
          ],
          [
            "",
            ""
          ],
          [
            "MADDE 353-",
            "Fatura ve benzeri evrak verilmemesi ve alınmaması ile diğer şekil ve usul hükümlerine uyulmaması",
            ""
          ],
          [
            "",
            "1- Elektronik belge olarak düzenlenmesi gerekenler dahil olmak üzere fatura, gider pusulası, müstahsil makbuzu, serbest meslek makbuzu verilmemesi, alınmaması\n- Bir takvim yılı içinde her bir belge nevine ilişkin olarak kesilecek toplam ceza",
            "2.200\n \n \n \n1.100.000"
          ],
          [
            "",
            "4- Hazine ve Maliye Bakanlığınca tutulma ve günü gününe kayıt edilme mecburiyeti getirilen defterlerin; bulundurulmaması, günü gününe kayıt yapılmaması, yetkililere ibraz edilmemesi ile levha bulundurma ve asma mecburiyetine uyulmaması",
            "1.100"
          ],
          [
            "",
            "6- Belirlenen muhasebe standartlarına, tek düzen hesap planına ve mali tablolara ilişkin usul ve esaslar ile muhasebeye yönelik bilgisayar programlarının üretilmesine ilişkin kural ve standartlara uymayanlara",
            "26.000"
          ],
          [
            "",
            "7- Kamu kurum ve kuruluşları ile gerçek ve tüzel kişilerce yapılacak işlemlerde kullanılma zorunluluğu getirilen vergi numarasını kullanmaksızın işlem yapanlara",
            "1.300"
          ],
          [
            "",
            "9- 4358 sayılı Kanun uyarınca vergi kimlik numarası kullanma zorunluluğu getirilen kuruluşlardan yaptıkları işlemlere ilişkin bildirimleri, belirlenen standartlarda ve zamanda yerine getirmeyenlere",
            "5.500"
          ],
          [
            "MADDE 355",
            "b) Damga vergisinde\n-Her bir kağıt için kesilecek özel usulsüzlük cezası (En az)",
            "9"
          ],
          [
            "MÜKERRER MADDE 355-",
            "Bilgi vermekten çekinenler ile 107/A, mükerrer 242, 256, 257 ve mükerrer 257 ci madde hükmüne uymayanlar için ceza",
            ""
          ],
          [
            "",
            "1-Birinci sınıf tüccarlar ile serbest meslek erbabı hakkında",
            "7.500"
          ],
          [
            "",
            "Elektronik tebligat adresi alma mecburiyetine uymayanlar için\n-Birinci sınıf tüccarlar ile serbest meslek erbabı hakkında",
            "4.400"
          ],
          [
            "Tahsilat ve ödemelerini banka, benzeri finans kurumları veya posta idarelerince düzenlenen belgelerle tevsik etme zorunluluğuna uymayanlara bir takvim yılı içinde kesilecek toplam özel usulsüzlük cezası",
            "5.500.000"
          ]
        ],
        "caption": ""
      }
    ],
    "lists": [
      {
        "type": "ul",
        "items": [
          "",
          "",
          "",
          "",
          "Email Gönder"
        ]
      },
      {
        "type": "ul",
        "items": [
          "2022-495 sayılı genelyazı"
        ]
      }
    ],
    "forms": []
  },
  "raw_html": "﻿<!DOCTYPE html>\n\n<html>\n\n<head>\n\n   <title>2022-495 sayılı genelyazı</title>\n\n   <meta http-equiv=\"X-UA-Compatible\" content=\"IE=edge\" />\n\n   <meta name=\"viewport\" content=\"width=device-width, user-scalable=yes, initial-scale=1, minimum-scale=1\" />\n\n   <meta name=\"generator\" content=\"Help &amp; Manual\" />\n\n   <meta name=\"keywords\" content=\"\" />\n\n   <meta http-equiv=\"Content-Type\" content=\"text/html; charset=UTF-8\" />\n\n   <meta http-equiv=\"content-language\" content=\"tr\" />\n\n   <meta name=\"description\" content=\"Ankara, 31.12.2022 Mali Danışmanlık-290-58377 Özü: Vergi Usul Kanunu ve Gelir Vergisi Kanununda yer alan ve 2023 Yılında uygulanacak olan bazı maktu had ve miktarlar hk.\" />\n\n   <link rel=\"canonical\" content=\"noterlikrehberi.net/rehber/index.html?2022-495-sayili-genelyazi.html\" />\n\n   <meta http-equiv=\"Content-Style-Type\" content=\"text/css\" />\n\n   <link rel=\"shortcut icon\" href=\"noterlikrehberi.net/rehber/favicon.ico\" />\n\n   <link type=\"text/css\" href=\"default.css\" rel=\"stylesheet\" />\n\n   <link id=\"tabscheme\" type=\"text/css\" href=\"hm_topic.css\" rel=\"stylesheet\" />   \n\n<style type=\"text/css\">\n\n/* No header topics */\n\n\n\n/* Breadcrumb trail */\n\np#breadcrumbs {\n\nfont-family: Verdana, Tahoma, Helvetica, Sans-Serif;   padding: 2px 0 1px 2px;\n\n   margin: 0;\n\n   font-size: 8pt; \n\n   color: #777777;\n\n   }   \n\np#breadcrumbs a { color: #777777; text-decoration: none;}\n\np#breadcrumbs a:visited {color: #777777;}\n\np#breadcrumbs a:hover { color: #000000; border-bottom: 1px dotted #000000; }\n\n\n\n/* Search hightlight color */\n\nspan.highlight {background-color: #ffff40;}\n\n  div#hmsocialmedia {\n\n  min-width: 606px;\n\n  }\n\n</style>\n\n<script type=\"text/javascript\">\n\nvar hmHeaderTopic = true;\n\n\n\n</script> \n\n<!--[if IE 9]>\n\n<link id=\"iesvgcss\" rel=\"stylesheet\" type=\"text/css\" href=\"hm_webhelp_svg.css\" />\n\n<![endif]-->\t\n\n<script src=\"jquery.js\"></script>\n\n<script type=\"text/javascript\" src=\"jquery.tools.min.js\"></script>\n\n<script type=\"text/javascript\" src=\"jquery.scrollTo-min.js\"></script>\n\n<script type=\"text/javascript\"> \n\n// General topic variables\n\nvar tVars = {\n\n   hmHelpPage: \"index.html\",\n\n   nextP: \"\",\n\n   prevP: \"\",\n\n   currP: \"2022-495-sayili-genelyazi.html\",\n\n   descr: document.querySelector(\"meta[name='description']\").getAttribute(\"content\"),\n\n   keys: \"\",\n\n   defP: \"fihrist.html\",\n\n   mailUrl: \"\",\n\n   mailUrlQuery: \"\",\n\n   projectTitle: \"Noterlik Rehberi\",\n\n   titleP: \"2022-495 sayılı genelyazı\",\n\n   mailsubject: \"Tavsiye: Noterlik Rehberi - 2022-495 sayılı genelyazı &nbsp; &nbsp;NOTERLİK MEVZUATI DİZİNİ&nbsp; &nbsp;NOTERLİK İŞLEMLERİ DİZİNİ&nbsp; &nbsp;GENELGELER GENEL YAZILAR&nbsp; &nbsp;48 SAYILI GENELGE\",\n\n   sharesubject: \"Noterlik Rehberi - 2022-495 sayılı genelyazı &nbsp; &nbsp;NOTERLİK MEVZUATI DİZİNİ&nbsp; &nbsp;NOTERLİK İŞLEMLERİ DİZİNİ&nbsp; &nbsp;GENELGELER GENEL YAZILAR&nbsp; &nbsp;48 SAYILI GENELGE\",\n\n   simplesubject: \"Konu ile ilgili tavsiyede bulunmak istiyorum.\",\n\n   mailid: \"2022-495-sayili-genelyazi\",\n\n   mailpath: \"ÖNSÖZ /\",\n\n   mailbody: \"Merhaba, Yukarıda başlığı yazılı konu hakkindaki tavsiyelerim-sorularım şunlardır.\",\n\n   cliptab: 15,\n\n   cliptitle: 60,\n\n   fbtype: false,\n\n   header: true,\n\n   background: \"bg.png\",\n\n   tablesReady: false,\n\n   togglesReady: false,\n\n   webRedirect: false,\n\n   topicTitleBar: false,\n\n   titleBarContent: \"Konu\",\n\n   printFooter: true,\n\n   zoomTip: \"Resmi büyüt\",\n\n   autoPrint: true,\n\n   monoPrint: true,\n\n   printMode: false,\n\n   isEWriter: false,\n\n   printButton: \"Yazdır\",\n\n   printButtonTip: \"Bu konuyu yazdır\",\n\n   compilehash: (function () {\n\n\t\tvar outVal = 0, t= \"Noterlik Rehberi2024\";\n\n\t\tfor (var x = 0; x < t.length; x++) {\n\n\t\t\toutVal = outVal + (t.charCodeAt(x)*(x+2));\n\n\t\t}\n\n\t\treturn (outVal*697).toString(32) + \"_\";\n\n\t})()\n\n   };\n\n \n\n// Popup configuration\n\n var hmpBShadow = true;\n\n var hmPopSmallDim = 500;\n\n var hmPopKillVideo = true;\n\n // AutoTOC variables\n\n var hmatocvars = {\n\n   atoc_show: false,\n\n   atoc_title: \"\",\n\n   atoc_tip: \"Git:&amp;nbsp;\",\n\n   atoc_minHeaders: 3,\n\n   atoc_btntip_off: \"\",\n\n   atoc_btntip_on: \"Göster/Gizle\",\n\n   atoc_toptip: \"Sayfa Başına Git\",\n\n   atoc_top: \"Sayfa Başına Git\",\n\n   atoc_bg: \"#f6f6f6\",\n\n   atoc_border: \"#c0c0c0\",\n\n   atoc_linkcolor: \"#444\",\n\n   atoc_linklimit: 45,\n\n   atoc_hovercolor: \"#000\",\n\n   atoc_hoverbgcolor: \"#e0e0e0\"\n\n}\n\n// Sortable tables\n\nvar sortVars = {\n\n   europeandate: false,\n\n   germanNumbers: false,\n\n   imagePath: \"\",\n\n   image_up: \"arrow-up.gif\",\n\n   image_down: \"arrow-down.gif\",\n\n   image_empty: \"arrow-empty.gif\",\n\n   image_none: \"arrow-none.gif\",\n\n   sort_tip: \"Sırala\",\n\n   umlauts: \"true\"\n\n   }\n\n\n\n</script>\n\n\n\n\n\n<script type=\"text/javascript\" src=\"//platform.linkedin.com/in.js\"></script>\n\n<script type=\"text/javascript\" src=\"helpman_settings.js\"></script>\n\n<script type=\"text/javascript\" src=\"helpman_topicinit.js\"></script>\n\n<script type=\"text/javascript\" src=\"hmtopic.js\"></script>\n\n<script type=\"text/javascript\" src=\"hmpopups.js\"></script>\n\n<script type=\"text/javascript\"> /* Insert your own JS code or external script file reference for the HTML Page template here */\n\n</script>\n\n   <script type=\"text/javascript\" src=\"hmpopup_html.js\"></script>\n\n\n\n   <script type=\"text/javascript\">\n\n     HMSyncTOC(\"index.html\", \"2022-495-sayili-genelyazi.html\");\n\n   </script>\n\n   <script type=\"text/javascript\" src=\"highlight.js\"></script>\n\n   <script type=\"text/javascript\">\n\n     $(document).ready(function(){highlight();});\n\n   </script>\n\n</head>\n\n<body>  \n\n<!-- Help & Manual Premium Pack templates by Tim Green, Copyright (c) 2011-2017, All Rights Reserved -->\n\n<!--ZOOMSTOP-->\n\n<div id=\"hmsocialmedia\">\n\n\t<ul class=\"social-buttons\">\n\n\t<li>\n\n\t\t<div class=\"fb-button\">\n\n\t\t<iframe src=\"https://www.facebook.com/plugins/like.php?href=noterlikrehberi.net/rehber/index.html?2022-495-sayili-genelyazi.html\"\n\n        scrolling=\"no\" frameborder=\"0\"\n\n        style=\"border:none; width:300px; height:26px\"></iframe>\n\n\t\t</div>\n\n\t</li>\n\n\t<li>\n\n\t<a id=\"tweetthis\" href=\"https://twitter.com/share\" class=\"twitter-share-button\" data-url=\"noterlikrehberi.net/rehber/index.html?2022-495-sayili-genelyazi.html\" data-via=\"true\" data-size=\"default\"></a>\n\n\t<script>window.twttr=(function(d,s,id){var js,fjs=d.getElementsByTagName(s)[0];if(!d.getElementById(id)){js=d.createElement(s);js.id=id;js.src=\"//platform.twitter.com/widgets.js\";fjs.parentNode.insertBefore(js,fjs);}})(document,\"script\",\"twitter-wjs\");var hideTwitter = setInterval(function(){var $twitButton=$('[id*=twitter]');if($twitButton.length>1&&$($twitButton[1]).is(\":visible\")){$twitButton.hide();clearInterval(hideTwitter);}},50);</script>\n\n\t</li>\n\n\t<li>\n\n\t\t<div class=\"googleplusone-button\">\n\n                <g:plusone size=\"medium\" count=\"false\" href=\"noterlikrehberi.net/rehber/index.html?2022-495-sayili-genelyazi.html\"></g:plusone>\n\n                </div>\n\n\t\t<script type=\"text/javascript\">\n\n\t\twindow.___gcfg = {lang: 'tr-TR'};\n\n      (function(){var po = document.createElement('script'); po.type = 'text/javascript'; po.async = true;po.src = 'https://apis.google.com/js/plusone.js';var s = document.getElementsByTagName('script')[0]; s.parentNode.insertBefore(po, s);})();\n\n    </script>\n\n                \n\n\t</li> \n\n\t<li>\n\n\t\t<div class=\"linkedin-button\"><script type=\"IN/Share\" data-url=\"noterlikrehberi.net/rehber/index.html?2022-495-sayili-genelyazi.html\"></script></div>\n\n\t</li>\n\n\t<li>\n\n\t\t<div id=\"mailthisbutton\"><a href=\"mailto:?body=noterlikrehberi.net/rehber/index.html%3F2022-495-sayili-genelyazi.html\" class=\"sbutton\">\n\n\t\t<span id=\"sbuttontext\">Email Gönder</span>\n\n\t\t</a></div>\n\n\t</li> \n\n\t</ul>\n\n\t</div>\n\n\n\n\n\n<ul id=\"topictabs\" class=\"tabs\">\n\n<li id=\"indextab\" class=\"hmtabs\"><a href=\"#\" id=\"indextablink\" class=\"current\"><span>2022-495 sayılı genelyazı</span></a></li>\n\n</ul>\n\n<div id=\"hmbox\">\n\n<div id=\"hmheader\">\n\n<div id=\"hmheadercontents\">\n\n<p id=\"breadcrumbs\">\n\n<b><span class=\"sync-toc\"><a rel=\"nofollow\" class=\"sync-toc-link\" href=\"index.html?2022-495-sayili-genelyazi.html\" target=\"_top\">&lt;&lt;&nbsp;Fihrist-Ana sayfa&nbsp;&gt;&gt;</a>&nbsp;&nbsp;</span><span class=\"sync-toc-off\"></span></b><span class=\"sync-toc-off\">\n\n</span></p> \n\n<h1 class=\"p_Heading1\"><span class=\"f_Heading1\">2022-495 sayılı genelyazı</span></h1>\n\n<p class=\"p_Templatebuton_9\"><span class=\"f_Templatebuton_9\">  &nbsp; <a href=\"javascript:void(0);\" onclick=\"return hmshowPopup(event, popid_2147199316X, this);\" class=\"popuplink\" title=\"NOTERLİK MEVZUATI DİZİNİ\">NOTERLİK MEVZUATI DİZİNİ</a>  &nbsp; <a href=\"javascript:void(0);\" onclick=\"return hmshowPopup(event, popid_1447761013, this);\" class=\"popuplink\" title=\"NOTERLİK İŞLEMLERİ DİZİNİ\">NOTERLİK İŞLEMLERİ DİZİNİ</a>  &nbsp; <a href=\"javascript:void(0);\" onclick=\"return hmshowPopup(event, popid_2147199316X, this);\" class=\"popuplink\" title=\"NOTERLİK HAK.TÜM GENELGELER GENEL YAZILAR\"> GENELGELER GENEL YAZILAR</a>  &nbsp; <a href=\"ortak-cari-hesap-islemleri-hak-birlestirilmis-48-sayili-genelge.html\" class=\"topiclink\" title=\"ORTAK CARİ HESAP İŞLELERİ HAK. BİRLEŞTİRİLMİŞ 48 SAYILI GENELGE\">48 SAYILI GENELGE</a></span></p>\n\n\n\n</div>\n\n<div id=\"atocIcon\" class=\"navdivs\">\n\n<img class=\"navicon\" id=\"hmAtocLink\" src=\"contents_off.png\" alt=\"\" title=\"\" />\n\n<br /><span></span>\n\n</div>\n\n</div>\n\n<div id=\"autoTocWrapper\" class=\"topicmenu\"></div>\n\n<div id=\"idcontent\">\n\n<div id=\"unclicker\"></div>\n\n\n\n<!--ZOOMRESTART-->\n\n<p class=\"p_Normal\" style=\"background: #ffffff;\"><span style=\"color: #464646;\"> Ankara, 31.12.2022</span></p>\n\n<p class=\"p_Normal\" style=\"background: #ffffff;\"><span style=\"color: #464646;\">Mali Danışmanlık-</span><span style=\"font-weight: bold; color: #464646;\">290-58377</span></p>\n\n<p class=\"p_Normal\" style=\"background: #ffffff;\"><span style=\"color: #464646;\">Özü: Vergi Usul Kanunu ve Gelir Vergisi Kanununda yer alan ve 2023 Yılında uygulanacak olan bazı maktu had ve miktarlar hk.</span></p>\n\n<p class=\"p_Normal\" style=\"background: #ffffff;\"><span style=\"color: #464646;\">&nbsp;</span></p>\n\n<p class=\"p_Normal\" style=\"background: #ffffff;\"><span style=\"color: #464646;\">&nbsp;</span></p>\n\n<p class=\"p_Normal\" style=\"background: #ffffff;\"><span style=\"color: #464646;\">............. NOTER ODASI BAŞKANLIĞINA</span></p>\n\n<p class=\"p_Normal\" style=\"background: #ffffff;\"><span style=\"color: #464646;\">............. NOTERLİĞİNE</span></p>\n\n<p class=\"p_Normal\" style=\"background: #ffffff;\"><span style=\"color: #464646;\">&nbsp;</span></p>\n\n<p class=\"p_Normal\" style=\"background: #ffffff;\"><span style=\"color: #464646; text-decoration: underline;\">&nbsp;</span></p>\n\n<p class=\"p_Normal\" style=\"background: #ffffff;\"><span style=\"color: #464646;\">Hazine ve Maliye Bakanlığınca hazırlanan ve <a href=\"https://www.resmigazete.gov.tr/fihrist?tarih=2022-12-30&amp;mukerrer=2\" target=\"_blank\" onclick=\"return HMTrackTopiclink(this);\" class=\"weblink\">Resmi Gazete’nin 30 Aralık 2022 günlü ve 32059 (2. Mükerrer) nüshasında yayımlanan</a></span></p>\n\n<p class=\"p_Normal\" style=\"background: #ffffff;\"><span style=\"color: #464646;\">1- <a href=\"https://www.resmigazete.gov.tr/eskiler/2022/12/20221230M2-15.htm\" target=\"_blank\" onclick=\"return HMTrackTopiclink(this);\" class=\"weblink\">544. Sıra No.lu Vergi Usul Kanunu Genel Tebliği,</a></span></p>\n\n<p class=\"p_Normal\" style=\"background: #ffffff;\"><span style=\"color: #464646;\">2- <a href=\"https://www.resmigazete.gov.tr/eskiler/2022/12/20221230M2-12.htm\" target=\"_blank\" onclick=\"return HMTrackTopiclink(this);\" class=\"weblink\">322</a> ve <a href=\"https://www.resmigazete.gov.tr/eskiler/2022/12/20221230M2-13.htm\" target=\"_blank\" onclick=\"return HMTrackTopiclink(this);\" class=\"weblink\">323.Seri No.lu Gelir Vergisi Kanunu Genel Tebliğleri</a>,</span></p>\n\n<p class=\"p_Normal\" style=\"background: #ffffff;\"><span style=\"color: #464646;\">Yayımlanmış ve bu Tebliğlerde 01.01.2023 tarihinden itibaren uygulanacak olan bazı maktu had ve miktarlar yeniden tespit edilmiş bulunmaktadır.</span></p>\n\n<p class=\"p_Normal\" style=\"background: #ffffff;\"><span style=\"color: #464646;\">Sözü edilen Tebliğlerin noterlikleri ilgilendiren bölümleri aşağıda belirtilmiştir</span></p>\n\n<p class=\"p_Normal\" style=\"background: #ffffff;\"><span style=\"color: #464646;\">Bilgi edinilmesini rica ederim.</span></p>\n\n<p class=\"p_Normal\" style=\"background: #ffffff;\"><span style=\"color: #464646;\">&nbsp;</span></p>\n\n<p class=\"p_Normal\" style=\"background: #ffffff;\"><span style=\"color: #464646;\"> </span><span style=\"font-weight: bold; color: #464646;\">Emine ÇAĞLAYAN</span></p>\n\n<p class=\"p_Normal\" style=\"background: #ffffff;\"><span style=\"font-weight: bold; color: #464646;\"> Başkan</span></p>\n\n<p class=\"p_Normal\" style=\"background: #ffffff;\"><span style=\"color: #464646;\">&nbsp;</span></p>\n\n<p class=\"p_Normal\" style=\"background: #ffffff;\"><span style=\"color: #464646;\">&nbsp;</span></p>\n\n<p class=\"p_Normal\" style=\"background: #ffffff;\"><span style=\"color: #464646;\">&nbsp;</span></p>\n\n<p class=\"p_Normal\" style=\"background: #ffffff;\"><span style=\"color: #464646;\">&nbsp;</span></p>\n\n<p class=\"p_Normal\" style=\"background: #ffffff;\"><span style=\"font-weight: bold; color: #464646;\">GENELYAZI:( 495)</span><span style=\"color: #464646;\"> &nbsp;</span></p>\n\n<p class=\"p_Normal\" style=\"background: #ffffff;\"><span style=\"color: #464646;\">&nbsp;</span></p>\n\n<hr style=\"height:1px; color:#000000; border-width:0; background-color:#000000;\" /><p class=\"p_Normal\" style=\"background: #ffffff;\"><span style=\"font-weight: bold; color: #464646;\">&nbsp;</span></p>\n\n<p class=\"p_Normal\" style=\"text-align: center; background: #ffffff;\"><span style=\"font-weight: bold; color: #464646;\">VERGİ USUL KANUNU GENEL TEBLİĞİ</span></p>\n\n<p class=\"p_Normal\" style=\"text-align: center; background: #ffffff;\"><span style=\"font-weight: bold; color: #464646;\">(SIRA NO: 544)</span></p>\n\n<p class=\"p_Normal\" style=\"background: #ffffff;\"><span style=\"font-weight: bold; color: #464646;\">&nbsp;</span></p>\n\n<p class=\"p_Normal\" style=\"background: #ffffff;\"><span style=\"font-weight: bold; color: #464646;\">Amaç</span></p>\n\n<p class=\"p_Normal\" style=\"background: #ffffff;\"><span style=\"font-weight: bold; color: #464646;\">MADDE 1 –</span><span style=\"color: #464646;\"> (1) Bu Tebliğin amacı, 4/1/1961 tarihli ve 213 sayılı Vergi Usul Kanununun 104, mükerrer 115, 153/A, 177, 232, 252, mükerrer 257, 313, 323, 343, 352 (Kanuna Bağlı Cetvel), 353, 355, mükerrer 355, 370, EK 1 ve EK 11 inci maddelerinde yer alıp 2021 yılında uygulanan had ve tutarların yeniden değerleme oranında artırılması suretiyle 1/1/2023 tarihi itibarıyla uygulanacak had ve tutarların belirlenmesine ilişkin hususların açıklanmasıdır.</span></p>\n\n<p class=\"p_Normal\" style=\"background: #ffffff;\"><span style=\"color: #464646;\">&nbsp;</span></p>\n\n<p class=\"p_Normal\" style=\"background: #ffffff;\"><span style=\"font-weight: bold; color: #464646;\">Yasal düzenlemeler</span></p>\n\n<p class=\"p_Normal\" style=\"background: #ffffff;\"><span style=\"font-weight: bold; color: #464646;\">MADDE 2 –</span><span style=\"color: #464646;\"> (1) 213 sayılı Kanunun mükerrer 414 üncü maddesinin üçüncü fıkrasında, “Bu Kanunda yer alan maktu hadler ile asgari ve azami miktarları belirtilmiş olan para ile ödenecek ceza miktarları, her yıl bir önceki yıla ilişkin olarak bu Kanun uyarınca belirlenen yeniden değerleme oranında artırılmak suretiyle uygulanır. Bu şekilde hesaplanan maktu had ve miktarların yüzde beşini aşmayan kesirler dikkate alınmaz. Cumhurbaşkanı, bu suretle tespit edilen had ve miktarları yarısına kadar artırmaya veya indirmeye, nispi hadleri ise iki katına kadar artırmaya veya yarısına kadar indirmeye veya tekrar kanuni seviyesine getirmeye yetkilidir.” hükmü yer almaktadır.</span></p>\n\n<p class=\"p_Normal\" style=\"background: #ffffff;\"><span style=\"color: #464646;\">&nbsp;</span></p>\n\n<p class=\"p_Normal\" style=\"background: #ffffff;\"><span style=\"font-weight: bold; color: #464646;\">Yeniden değerleme oranında artırılan had ve tutarlar</span></p>\n\n<p class=\"p_Normal\" style=\"background: #ffffff;\"><span style=\"font-weight: bold; color: #464646;\">MADDE 3 – </span><span style=\"color: #464646;\">(1) 213 sayılı Kanunun mükerrer 414 üncü maddesi ile mezkur Kanunun 104 üncü maddesinin üçüncü fıkrası hükmü uyarınca aynı Kanunun 104, mükerrer 115, 153/A, 177, 232, 252, mükerrer 257, 313, 323, 343, 352 (Kanuna Bağlı Cetvel), 353, 355, mükerrer 355, 370, EK 1 ve EK 11 inci maddelerinde yer alıp 2022 yılında uygulanan had ve tutarların, 2022 yılı için %122,93 (yüz yirmi iki virgül doksan üç) olarak tespit edilen yeniden değerleme oranında artırılması, artırılan bu had ve tutarların Kanunun 104 üncü maddesinin birinci fıkrasının (4 numaralı) bendinde yer alan tutarın mezkur yetkiye istinaden yeniden artırılması suretiyle belirlenen ve 1/1/2023 tarihinden itibaren uygulanacak olan had ve tutarlar ekli listede gösterilmiştir.</span></p>\n\n<p class=\"p_Normal\" style=\"background: #ffffff;\"><span style=\"color: #464646;\">&nbsp;</span></p>\n\n<p class=\"p_Normal\" style=\"background: #ffffff;\"><span style=\"font-weight: bold; color: #464646;\">Yürürlük</span></p>\n\n<p class=\"p_Normal\" style=\"background: #ffffff;\"><span style=\"font-weight: bold; color: #464646;\">MADDE 4 –</span><span style=\"color: #464646;\"> (1) Bu Tebliğ 1/1/2023 tarihinde yürürlüğe girer.</span></p>\n\n<p class=\"p_Normal\" style=\"background: #ffffff;\"><span style=\"font-weight: bold; color: #464646;\">Yürütme</span></p>\n\n<p class=\"p_Normal\" style=\"background: #ffffff;\"><span style=\"font-weight: bold; color: #464646;\">MADDE 5 –</span><span style=\"color: #464646;\"> (1) Bu Tebliğ hükümlerini Hazine ve Maliye Bakanı yürütür.</span></p>\n\n<p class=\"p_Normal\" style=\"background: #ffffff;\"><span style=\"font-weight: bold; color: #464646;\">&nbsp;</span></p>\n\n<p class=\"p_Normal\" style=\"background: #ffffff;\"><span style=\"font-weight: bold; color: #464646;\">&nbsp;</span></p>\n\n<p class=\"p_Normal\" style=\"background: #ffffff;\"><span style=\"font-weight: bold; color: #464646;\">&nbsp;</span></p>\n\n<p class=\"p_Normal\" style=\"background: #ffffff;\"><span style=\"font-weight: bold; color: #464646;\">VERGİ USUL KANUNUNDA YER ALAN VE 01/01/2023 TARİHİNDEN GEÇERLİ OLMAK ÜZERE UYGULANACAK OLAN HAD VE MİKTARLAR</span></p>\n\n<p class=\"p_Normal\" style=\"background: #ffffff;\"><span style=\"font-weight: bold; color: #464646;\">&nbsp;</span></p>\n\n<div style=\"text-align: justify; text-indent: 0; padding: 0 0 0 0; margin: 0 0 0 0;\"><table style=\"width:100%; border:none; border-spacing:0; border-collapse:collapse;\">\n\n<tr>\n\n<td style=\"vertical-align:middle; width:146px; padding:0; border:solid thin #000000;\"><p class=\"p_Normal\"><span style=\"color: #464646;\">&nbsp;</span></p>\n\n<p class=\"p_Normal\"><span style=\"font-weight: bold; color: #464646;\">MADDE NO</span></p>\n\n</td>\n\n<td style=\"vertical-align:middle; width:562px; padding:0; border:solid thin #000000;\"><p class=\"p_Normal\"><span style=\"font-weight: bold; color: #464646;\"> &nbsp; &nbsp; &nbsp; &nbsp; &nbsp; &nbsp; &nbsp; &nbsp; &nbsp; &nbsp; &nbsp; &nbsp; &nbsp; &nbsp; &nbsp; &nbsp; </span></p>\n\n<p class=\"p_Normal\"><span style=\"font-weight: bold; color: #464646;\">KONUSU</span></p>\n\n</td>\n\n<td style=\"vertical-align:middle; width:73px; padding:0; border:solid thin #000000;\"><p class=\"p_Normal\"><span style=\"font-weight: bold; color: #464646;\">2023 Yılında</span></p>\n\n<p class=\"p_Normal\"><span style=\"font-weight: bold; color: #464646;\">Uygulanacak Miktar (TL)</span><span style=\"color: #464646;\"> </span></p>\n\n</td>\n\n</tr>\n\n<tr>\n\n<td style=\"vertical-align:middle; width:146px; padding:0; border:solid thin #000000;\"><p class=\"p_Normal\"><span style=\"font-weight: bold; color: #464646;\">MADDE 177-</span></p>\n\n</td>\n\n<td style=\"vertical-align:middle; width:562px; padding:0; border:solid thin #000000;\"><p class=\"p_Normal\"><span style=\"font-weight: bold; color: #464646;\">Bilanço hesabı esasına göre defter tutma hadleri</span></p>\n\n</td>\n\n<td style=\"vertical-align:middle; width:73px; padding:0; border:solid thin #000000;\"><p class=\"p_Normal\"><span style=\"color: #464646;\">&nbsp;</span></p>\n\n</td>\n\n</tr>\n\n<tr>\n\n<td style=\"vertical-align:middle; width:146px; padding:0; border:solid thin #000000;\"><p class=\"p_Normal\"><span style=\"color: #464646;\">&nbsp;</span></p>\n\n</td>\n\n<td style=\"vertical-align:middle; width:562px; padding:0; border:solid thin #000000;\"><p class=\"p_Normal\"><span style=\"color: #464646;\">1- Yıllık;</span></p>\n\n<p class=\"p_Normal\"><span style=\"color: #464646;\"> - Alış tutarı</span></p>\n\n<p class=\"p_Normal\"><span style=\"color: #464646;\">- Satış tutarı</span></p>\n\n</td>\n\n<td style=\"vertical-align:middle; width:73px; padding:0; border:solid thin #000000;\"><p class=\"p_Normal\"><span style=\"font-weight: bold; color: #464646;\">&nbsp;</span></p>\n\n<p class=\"p_Normal\"><span style=\"font-weight: bold; color: #464646;\">890.000</span></p>\n\n<p class=\"p_Normal\"><span style=\"font-weight: bold; color: #464646;\">1.270.000</span></p>\n\n</td>\n\n</tr>\n\n<tr>\n\n<td style=\"vertical-align:middle; width:146px; padding:0; border:solid thin #000000;\"><p class=\"p_Normal\"><span style=\"color: #464646;\">&nbsp;</span></p>\n\n</td>\n\n<td style=\"vertical-align:middle; width:562px; padding:0; border:solid thin #000000;\"><p class=\"p_Normal\"><span style=\"color: #464646;\">2- Yıllık gayrisafi iş hasılatı</span></p>\n\n</td>\n\n<td style=\"vertical-align:middle; width:73px; padding:0; border:solid thin #000000;\"><p class=\"p_Normal\"><span style=\"font-weight: bold; color: #464646;\">440.000</span></p>\n\n</td>\n\n</tr>\n\n<tr>\n\n<td style=\"vertical-align:middle; width:146px; padding:0; border:solid thin #000000;\"><p class=\"p_Normal\"><span style=\"color: #464646;\">&nbsp;</span></p>\n\n</td>\n\n<td style=\"vertical-align:middle; width:562px; padding:0; border:solid thin #000000;\"><p class=\"p_Normal\"><span style=\"color: #464646;\">3- İş hasılatının beş katı ile yıllık satış tutarının toplamı</span></p>\n\n</td>\n\n<td style=\"vertical-align:middle; width:73px; padding:0; border:solid thin #000000;\"><p class=\"p_Normal\"><span style=\"font-weight: bold; color: #464646;\">890.000</span></p>\n\n</td>\n\n</tr>\n\n<tr>\n\n<td style=\"vertical-align:middle; width:146px; padding:0; border:solid thin #000000;\"><p class=\"p_Normal\"><span style=\"font-weight: bold; color: #464646;\">MADDE 232-</span></p>\n\n</td>\n\n<td style=\"vertical-align:middle; width:562px; padding:0; border:solid thin #000000;\"><p class=\"p_Normal\"><span style=\"font-weight: bold; color: #464646;\">Fatura kullanma mecburiyeti</span></p>\n\n</td>\n\n<td style=\"vertical-align:middle; width:73px; padding:0; border:solid thin #000000;\"><p class=\"p_Normal\"><span style=\"font-weight: bold; color: #464646;\">4.400</span></p>\n\n</td>\n\n</tr>\n\n<tr>\n\n<td style=\"vertical-align:middle; width:146px; padding:0; border:solid thin #000000;\"><p class=\"p_Normal\"><span style=\"font-weight: bold; color: #464646;\">MADDE 313-</span></p>\n\n</td>\n\n<td style=\"vertical-align:middle; width:562px; padding:0; border:solid thin #000000;\"><p class=\"p_Normal\"><span style=\"font-weight: bold; color: #464646;\">&nbsp;</span></p>\n\n<p class=\"p_Normal\"><span style=\"font-weight: bold; color: #464646;\">Doğrudan gider yazılacak demirbaş ve peştemallıklar</span></p>\n\n</td>\n\n<td style=\"vertical-align:middle; width:73px; padding:0; border:solid thin #000000;\"><p class=\"p_Normal\"><span style=\"font-weight: bold; color: #464646;\">&nbsp;</span></p>\n\n<p class=\"p_Normal\"><span style=\"font-weight: bold; color: #464646;\">4.400</span></p>\n\n</td>\n\n</tr>\n\n<tr>\n\n<td style=\"vertical-align:middle; width:146px; padding:0; border:solid thin #000000;\"><p class=\"p_Normal\"><span style=\"font-weight: bold; color: #464646;\">&nbsp;</span></p>\n\n<p class=\"p_Normal\"><span style=\"font-weight: bold; color: #464646;\">MADDE 343-</span></p>\n\n</td>\n\n<td style=\"vertical-align:middle; width:562px; padding:0; border:solid thin #000000;\"><p class=\"p_Normal\"><span style=\"font-weight: bold; color: #464646;\">&nbsp;</span></p>\n\n<p class=\"p_Normal\"><span style=\"font-weight: bold; color: #464646;\">En az ceza haddi</span></p>\n\n</td>\n\n<td style=\"vertical-align:middle; width:73px; padding:0; border:solid thin #000000;\"><p class=\"p_Normal\"><span style=\"font-weight: bold; color: #464646;\">&nbsp;</span></p>\n\n</td>\n\n</tr>\n\n<tr>\n\n<td style=\"vertical-align:middle; width:146px; padding:0; border:solid thin #000000;\"><p class=\"p_Normal\"><span style=\"color: #464646;\">&nbsp;</span></p>\n\n</td>\n\n<td style=\"vertical-align:middle; width:562px; padding:0; border:solid thin #000000;\"><p class=\"p_Normal\"><span style=\"color: #464646;\">- Damga vergisinde</span></p>\n\n<p class=\"p_Normal\"><span style=\"color: #464646;\">- Diğer vergilerde</span></p>\n\n</td>\n\n<td style=\"vertical-align:middle; width:73px; padding:0; border:solid thin #000000;\"><p class=\"p_Normal\"><span style=\"font-weight: bold; color: #464646;\">55</span></p>\n\n<p class=\"p_Normal\"><span style=\"font-weight: bold; color: #464646;\">110</span></p>\n\n</td>\n\n</tr>\n\n<tr>\n\n<td style=\"vertical-align:middle; width:146px; padding:0; border:solid thin #000000;\"><p class=\"p_Normal\"><span style=\"font-weight: bold; color: #464646;\">&nbsp;</span></p>\n\n<p class=\"p_Normal\"><span style=\"font-weight: bold; color: #464646;\">MADDE 352- </span></p>\n\n<p class=\"p_Normal\"><span style=\"color: #464646;\">&nbsp;</span></p>\n\n</td>\n\n<td style=\"vertical-align:middle; width:562px; padding:0; border:solid thin #000000;\"><p class=\"p_Normal\"><span style=\"font-weight: bold; color: #464646;\">&nbsp;</span></p>\n\n<p class=\"p_Normal\"><span style=\"font-weight: bold; color: #464646;\">Usulsüzlük dereceleri ve cezaları</span></p>\n\n<p class=\"p_Normal\"><span style=\"font-weight: bold; color: #464646;\">(Kanuna bağlı cetvel)</span></p>\n\n</td>\n\n<td style=\"vertical-align:middle; width:73px; padding:0; border:solid thin #000000;\"><p class=\"p_Normal\"><span style=\"color: #464646;\">&nbsp;</span></p>\n\n</td>\n\n</tr>\n\n<tr>\n\n<td style=\"vertical-align:middle; width:146px; padding:0; border:solid thin #000000;\"><p class=\"p_Normal\"><span style=\"color: #464646;\">&nbsp;</span></p>\n\n</td>\n\n<td style=\"vertical-align:middle; width:562px; padding:0; border:solid thin #000000;\"><p class=\"p_Normal\"><span style=\"font-weight: bold; color: #464646;\">I inci derece usulsüzlükler</span></p>\n\n</td>\n\n<td style=\"vertical-align:middle; width:73px; padding:0; border:solid thin #000000;\"><p class=\"p_Normal\"><span style=\"color: #464646;\">&nbsp;</span></p>\n\n</td>\n\n</tr>\n\n<tr>\n\n<td style=\"vertical-align:middle; width:146px; padding:0; border:solid thin #000000;\"><p class=\"p_Normal\"><span style=\"color: #464646;\">&nbsp;</span></p>\n\n</td>\n\n<td style=\"vertical-align:middle; width:562px; padding:0; border:solid thin #000000;\"><p class=\"p_Normal\"><span style=\"color: #464646;\">2- Sermaye şirketi dışında kalan birinci sınıf tüccarlar ve serbest meslek erbabı &nbsp; &nbsp; &nbsp; &nbsp; &nbsp; &nbsp; &nbsp; &nbsp; &nbsp; &nbsp; &nbsp; &nbsp; &nbsp; &nbsp; &nbsp; &nbsp; &nbsp; &nbsp; &nbsp; &nbsp; &nbsp; &nbsp; &nbsp; &nbsp; &nbsp; &nbsp; &nbsp; &nbsp; &nbsp; &nbsp; &nbsp; &nbsp; &nbsp; &nbsp; &nbsp; &nbsp; &nbsp; </span></p>\n\n</td>\n\n<td style=\"vertical-align:middle; width:73px; padding:0; border:solid thin #000000;\"><p class=\"p_Normal\"><span style=\"font-weight: bold; color: #464646;\">&nbsp;</span></p>\n\n<p class=\"p_Normal\"><span style=\"font-weight: bold; color: #464646;\">420</span></p>\n\n</td>\n\n</tr>\n\n<tr>\n\n<td style=\"vertical-align:middle; width:146px; padding:0; border:solid thin #000000;\"><p class=\"p_Normal\"><span style=\"color: #464646;\">&nbsp;</span></p>\n\n</td>\n\n<td style=\"vertical-align:middle; width:562px; padding:0; border:solid thin #000000;\"><p class=\"p_Normal\"><span style=\"font-weight: bold; color: #464646; text-decoration: underline;\">II nci derece usulsüzlükler</span><span style=\"font-weight: bold; color: #464646;\"> &nbsp; &nbsp; </span><span style=\"font-style: italic; font-weight: bold; color: #464646;\"> &nbsp; &nbsp; &nbsp; &nbsp; &nbsp; &nbsp; &nbsp; &nbsp; &nbsp; &nbsp; &nbsp; &nbsp; &nbsp; &nbsp; &nbsp;</span></p>\n\n</td>\n\n<td style=\"vertical-align:middle; width:73px; padding:0; border:solid thin #000000;\"><p><span style=\"color: #464646;\">&nbsp;</span></p>\n\n</td>\n\n</tr>\n\n<tr>\n\n<td style=\"vertical-align:middle; width:146px; padding:0; border:solid thin #000000;\"><p class=\"p_Normal\"><span style=\"color: #464646;\">&nbsp;</span></p>\n\n</td>\n\n<td style=\"vertical-align:middle; width:562px; padding:0; border:solid thin #000000;\"><p class=\"p_Normal\"><span style=\"color: #464646;\">2- Sermaye şirketi dışında kalan birinci sınıf tüccarlar ve serbest meslek erbabı</span></p>\n\n</td>\n\n<td style=\"vertical-align:middle; width:73px; padding:0; border:solid thin #000000;\"><p class=\"p_Normal\"><span style=\"font-weight: bold; color: #464646;\">&nbsp;</span></p>\n\n<p class=\"p_Normal\"><span style=\"font-weight: bold; color: #464646;\">210</span></p>\n\n</td>\n\n</tr>\n\n<tr>\n\n<td colspan=\"2\"  style=\"vertical-align:middle; width:709px; padding:0; border:solid thin #000000;\"><p class=\"p_Normal\"><span style=\"font-weight: bold; color: #464646;\">&nbsp;</span></p>\n\n</td>\n\n<td style=\"vertical-align:middle; width:73px; padding:0; border:solid thin #000000;\"><p class=\"p_Normal\"><span style=\"color: #464646;\">&nbsp;</span></p>\n\n</td>\n\n</tr>\n\n<tr>\n\n<td style=\"vertical-align:middle; width:146px; padding:0; border:solid thin #000000;\"><p class=\"p_Normal\"><span style=\"font-weight: bold; color: #464646;\">MADDE 353-</span></p>\n\n</td>\n\n<td style=\"vertical-align:middle; width:562px; padding:0; border:solid thin #000000;\"><p class=\"p_Normal\"><span style=\"font-weight: bold; color: #464646;\">Fatura ve benzeri evrak verilmemesi ve alınmaması ile diğer şekil ve usul hükümlerine uyulmaması</span></p>\n\n</td>\n\n<td style=\"vertical-align:middle; width:73px; padding:0; border:solid thin #000000;\"><p><span style=\"color: #464646;\">&nbsp;</span></p>\n\n</td>\n\n</tr>\n\n<tr>\n\n<td style=\"vertical-align:middle; width:146px; padding:0; border:solid thin #000000;\"><p class=\"p_Normal\"><span style=\"color: #464646;\">&nbsp;</span></p>\n\n</td>\n\n<td style=\"vertical-align:middle; width:562px; padding:0; border:solid thin #000000;\"><p class=\"p_Normal\"><span style=\"color: #464646;\">1- Elektronik belge olarak düzenlenmesi gerekenler dahil olmak üzere fatura, gider pusulası, müstahsil makbuzu, serbest meslek makbuzu verilmemesi, alınmaması</span></p>\n\n<p class=\"p_Normal\"><span style=\"color: #464646;\">- Bir takvim yılı içinde her bir belge nevine ilişkin olarak kesilecek toplam ceza</span></p>\n\n</td>\n\n<td style=\"vertical-align:middle; width:73px; padding:0; border:solid thin #000000;\"><p class=\"p_Normal\"><span style=\"font-weight: bold; color: #464646;\">2.200</span></p>\n\n<p class=\"p_Normal\"><span style=\"font-weight: bold; color: #464646;\">&nbsp;</span></p>\n\n<p class=\"p_Normal\"><span style=\"font-weight: bold; color: #464646;\">&nbsp;</span></p>\n\n<p class=\"p_Normal\"><span style=\"font-weight: bold; color: #464646;\">&nbsp;</span></p>\n\n<p class=\"p_Normal\"><span style=\"font-weight: bold; color: #464646;\">1.100.000</span></p>\n\n</td>\n\n</tr>\n\n<tr>\n\n<td style=\"vertical-align:middle; width:146px; padding:0; border:solid thin #000000;\"><p class=\"p_Normal\"><span style=\"color: #464646;\">&nbsp;</span></p>\n\n</td>\n\n<td style=\"vertical-align:middle; width:562px; padding:0; border:solid thin #000000;\"><p class=\"p_Normal\"><span style=\"color: #464646;\">4- Hazine ve Maliye Bakanlığınca tutulma ve günü gününe kayıt edilme mecburiyeti getirilen defterlerin; bulundurulmaması, günü gününe kayıt yapılmaması, yetkililere ibraz edilmemesi ile levha bulundurma ve asma mecburiyetine uyulmaması</span></p>\n\n</td>\n\n<td style=\"vertical-align:middle; width:73px; padding:0; border:solid thin #000000;\"><p class=\"p_Normal\"><span style=\"font-weight: bold; color: #464646;\">&nbsp;</span></p>\n\n<p class=\"p_Normal\"><span style=\"font-weight: bold; color: #464646;\">&nbsp;</span></p>\n\n<p class=\"p_Normal\"><span style=\"font-weight: bold; color: #464646;\">&nbsp;</span></p>\n\n<p class=\"p_Normal\"><span style=\"font-weight: bold; color: #464646;\">&nbsp;</span></p>\n\n<p class=\"p_Normal\"><span style=\"font-weight: bold; color: #464646;\">1.100</span></p>\n\n</td>\n\n</tr>\n\n<tr>\n\n<td style=\"vertical-align:middle; width:146px; padding:0; border:solid thin #000000;\"><p class=\"p_Normal\"><span style=\"color: #464646;\">&nbsp;</span></p>\n\n</td>\n\n<td style=\"vertical-align:middle; width:562px; padding:0; border:solid thin #000000;\"><p class=\"p_Normal\"><span style=\"color: #464646;\">6- Belirlenen muhasebe standartlarına, tek düzen hesap planına ve mali tablolara ilişkin usul ve esaslar ile muhasebeye yönelik bilgisayar programlarının üretilmesine ilişkin kural ve standartlara uymayanlara</span></p>\n\n</td>\n\n<td style=\"vertical-align:middle; width:73px; padding:0; border:solid thin #000000;\"><p class=\"p_Normal\"><span style=\"font-weight: bold; color: #464646;\">&nbsp;</span></p>\n\n<p class=\"p_Normal\"><span style=\"font-weight: bold; color: #464646;\">&nbsp;</span></p>\n\n<p class=\"p_Normal\"><span style=\"font-weight: bold; color: #464646;\">&nbsp;</span></p>\n\n<p class=\"p_Normal\"><span style=\"font-weight: bold; color: #464646;\">26.000</span></p>\n\n</td>\n\n</tr>\n\n<tr>\n\n<td style=\"vertical-align:middle; width:146px; padding:0; border:solid thin #000000;\"><p class=\"p_Normal\"><span style=\"color: #464646;\">&nbsp;</span></p>\n\n</td>\n\n<td style=\"vertical-align:middle; width:562px; padding:0; border:solid thin #000000;\"><p class=\"p_Normal\"><span style=\"color: #464646;\">7- Kamu kurum ve kuruluşları ile gerçek ve tüzel kişilerce yapılacak işlemlerde kullanılma zorunluluğu getirilen vergi numarasını kullanmaksızın işlem yapanlara</span></p>\n\n</td>\n\n<td style=\"vertical-align:middle; width:73px; padding:0; border:solid thin #000000;\"><p class=\"p_Normal\"><span style=\"font-weight: bold; color: #464646;\">&nbsp;</span></p>\n\n<p class=\"p_Normal\"><span style=\"font-weight: bold; color: #464646;\">&nbsp;</span></p>\n\n<p class=\"p_Normal\"><span style=\"font-weight: bold; color: #464646;\">1.300</span></p>\n\n</td>\n\n</tr>\n\n<tr>\n\n<td style=\"vertical-align:middle; width:146px; padding:0; border:solid thin #000000;\"><p class=\"p_Normal\"><span style=\"color: #464646;\">&nbsp;</span></p>\n\n</td>\n\n<td style=\"vertical-align:middle; width:562px; padding:0; border:solid thin #000000;\"><p class=\"p_Normal\"><span style=\"color: #464646;\">9</span><span style=\"font-weight: bold; color: #464646;\">-</span><span style=\"color: #464646;\"> 4358 sayılı Kanun uyarınca vergi kimlik numarası kullanma zorunluluğu getirilen kuruluşlardan yaptıkları işlemlere ilişkin bildirimleri, belirlenen standartlarda ve zamanda yerine getirmeyenlere</span></p>\n\n</td>\n\n<td style=\"vertical-align:middle; width:73px; padding:0; border:solid thin #000000;\"><p class=\"p_Normal\"><span style=\"font-weight: bold; color: #464646;\">&nbsp;</span></p>\n\n<p class=\"p_Normal\"><span style=\"font-weight: bold; color: #464646;\">&nbsp;</span></p>\n\n<p class=\"p_Normal\"><span style=\"font-weight: bold; color: #464646;\">&nbsp;</span></p>\n\n<p class=\"p_Normal\"><span style=\"font-weight: bold; color: #464646;\">5.500</span></p>\n\n</td>\n\n</tr>\n\n<tr>\n\n<td style=\"vertical-align:middle; width:146px; padding:0; border:solid thin #000000;\"><p class=\"p_Normal\"><span style=\"font-weight: bold; color: #464646;\">&nbsp;</span></p>\n\n<p class=\"p_Normal\"><span style=\"font-weight: bold; color: #464646;\">MADDE 355</span></p>\n\n</td>\n\n<td style=\"vertical-align:middle; width:562px; padding:0; border:solid thin #000000;\"><p class=\"p_Normal\"><span style=\"font-weight: bold; color: #464646;\">b) Damga vergisinde</span></p>\n\n<p class=\"p_Normal\"><span style=\"color: #464646;\">-Her bir kağıt için kesilecek özel usulsüzlük cezası (En az)</span></p>\n\n<p class=\"p_Normal\"><span style=\"font-weight: bold; color: #464646;\">&nbsp;</span></p>\n\n</td>\n\n<td style=\"vertical-align:middle; width:73px; padding:0; border:solid thin #000000;\"><p class=\"p_Normal\"><span style=\"font-weight: bold; color: #464646;\">&nbsp;</span></p>\n\n<p class=\"p_Normal\"><span style=\"font-weight: bold; color: #464646;\">9</span></p>\n\n<p class=\"p_Normal\"><span style=\"font-weight: bold; color: #464646;\">&nbsp;</span></p>\n\n</td>\n\n</tr>\n\n<tr>\n\n<td style=\"vertical-align:middle; width:146px; padding:0; border:solid thin #000000;\"><p class=\"p_Normal\"><span style=\"font-weight: bold; color: #464646;\">MÜKERRER MADDE 355-</span><span style=\"color: #464646;\"> </span></p>\n\n<p class=\"p_Normal\"><span style=\"font-weight: bold; color: #464646;\">&nbsp;</span></p>\n\n</td>\n\n<td style=\"vertical-align:middle; width:562px; padding:0; border:solid thin #000000;\"><p class=\"p_Normal\"><span style=\"font-weight: bold; color: #464646;\">Bilgi vermekten çekinenler ile 107/A, mükerrer 242, 256, 257 ve mükerrer 257 ci madde hükmüne uymayanlar için ceza</span><span style=\"color: #464646;\"> </span></p>\n\n</td>\n\n<td style=\"vertical-align:middle; width:73px; padding:0; border:solid thin #000000;\"><p class=\"p_Normal\"><span style=\"font-weight: bold; color: #464646;\">&nbsp;</span></p>\n\n</td>\n\n</tr>\n\n<tr>\n\n<td style=\"vertical-align:middle; width:146px; padding:0; border:solid thin #000000;\"><p><span style=\"color: #464646;\">&nbsp;</span></p>\n\n</td>\n\n<td style=\"vertical-align:middle; width:562px; padding:0; border:solid thin #000000;\"><p class=\"p_Normal\"><span style=\"color: #464646;\">1-Birinci sınıf tüccarlar ile serbest meslek erbabı hakkında </span></p>\n\n</td>\n\n<td style=\"vertical-align:middle; width:73px; padding:0; border:solid thin #000000;\"><p class=\"p_Normal\"><span style=\"font-weight: bold; color: #464646;\">7.500</span></p>\n\n</td>\n\n</tr>\n\n<tr>\n\n<td rowspan=\"2\"  style=\"vertical-align:middle; width:146px; padding:0; border:solid thin #000000;\"><p class=\"p_Normal\"><span style=\"color: #464646;\">&nbsp;</span></p>\n\n</td>\n\n<td style=\"vertical-align:middle; width:562px; padding:0; border:solid thin #000000;\"><p class=\"p_Normal\"><span style=\"font-weight: bold; color: #464646;\">&nbsp;</span></p>\n\n<p class=\"p_Normal\"><span style=\"font-weight: bold; color: #464646;\">Elektronik tebligat adresi alma mecburiyetine uymayanlar için</span></p>\n\n<p class=\"p_Normal\"><span style=\"color: #464646;\">-Birinci sınıf tüccarlar ile serbest meslek erbabı hakkında </span></p>\n\n</td>\n\n<td style=\"vertical-align:middle; width:73px; padding:0; border:solid thin #000000;\"><p class=\"p_Normal\"><span style=\"font-weight: bold; color: #464646;\">&nbsp;</span></p>\n\n<p class=\"p_Normal\"><span style=\"font-weight: bold; color: #464646;\">&nbsp;</span></p>\n\n<p class=\"p_Normal\"><span style=\"font-weight: bold; color: #464646;\">4.400</span></p>\n\n</td>\n\n</tr>\n\n<tr>\n\n<td style=\"vertical-align:middle; width:562px; padding:0; border:solid thin #000000;\"><p class=\"p_Normal\"><span style=\"color: #464646;\">Tahsilat ve ödemelerini banka, benzeri finans kurumları veya posta idarelerince düzenlenen belgelerle tevsik etme zorunluluğuna uymayanlara bir takvim yılı içinde kesilecek toplam özel usulsüzlük cezası</span></p>\n\n</td>\n\n<td style=\"vertical-align:middle; width:73px; padding:0; border:solid thin #000000;\"><p class=\"p_Normal\"><span style=\"font-weight: bold; color: #464646;\">&nbsp;</span></p>\n\n<p class=\"p_Normal\"><span style=\"font-weight: bold; color: #464646;\">&nbsp;</span></p>\n\n<p class=\"p_Normal\"><span style=\"font-weight: bold; color: #464646;\">&nbsp;</span></p>\n\n<p class=\"p_Normal\"><span style=\"font-weight: bold; color: #464646;\">5.500.000</span></p>\n\n</td>\n\n</tr>\n\n</table>\n\n</div>\n\n<p class=\"p_Normal\" style=\"background: #ffffff;\"><span style=\"background-color: #ffffff;\">&nbsp;</span></p>\n\n<hr style=\"height:1px; color:#000000; border-width:0; background-color:#000000;\" /><p class=\"p_Normal\" style=\"text-align: center; background: #ffffff;\"><span style=\"font-weight: bold; color: #464646;\">GELİR VERGİSİ GENEL TEBLİĞİ</span></p>\n\n<p class=\"p_Normal\" style=\"text-align: center; background: #ffffff;\"><span style=\"font-weight: bold; color: #464646;\">(SERİ NO: 322)</span></p>\n\n<p class=\"p_Normal\" style=\"background: #ffffff;\"><span style=\"color: #464646;\">&nbsp;</span></p>\n\n<p class=\"p_Normal\" style=\"background: #ffffff;\"><span style=\"font-weight: bold; color: #464646;\">BİRİNCİ BÖLÜM</span></p>\n\n<p class=\"p_Normal\" style=\"background: #ffffff;\"><span style=\"font-weight: bold; color: #464646;\">Amaç ve Kapsam</span></p>\n\n<p class=\"p_Normal\" style=\"background: #ffffff;\"><span style=\"font-weight: bold; color: #464646;\">&nbsp;</span></p>\n\n<p class=\"p_Normal\" style=\"background: #ffffff;\"><span style=\"font-weight: bold; color: #464646;\">Amaç ve kapsam</span></p>\n\n<p class=\"p_Normal\" style=\"background: #ffffff;\"><span style=\"font-weight: bold; color: #464646;\">MADDE 1- </span><span style=\"color: #464646;\">(1) Bu Tebliğin amacı; 31/12/1960 tarihli ve 193 sayılı Gelir Vergisi Kanununda 3/11/2022 tarihli ve 7420 sayılı Gelir Vergisi Kanunu ile Bazı Kanun ve Kanun Hükmünde Kararnamelerde Değişiklik Yapılmasına Dair Kanunla yapılan değişiklikler ile aynı Kanunun geçici 1 inci maddesinin uygulamasına ilişkin usul ve esasları düzenlemektir.</span></p>\n\n<p class=\"p_Normal\" style=\"background: #ffffff;\"><span style=\"font-weight: bold; color: #464646;\">….</span></p>\n\n<p class=\"p_Normal\" style=\"background: #ffffff;\"><span style=\"font-weight: bold; color: #464646;\">&nbsp;</span></p>\n\n<p class=\"p_Normal\" style=\"background: #ffffff;\"><span style=\"font-weight: bold; color: #464646;\">DÖRDÜNCÜ BÖLÜM</span></p>\n\n<p class=\"p_Normal\" style=\"background: #ffffff;\"><span style=\"font-weight: bold; color: #464646;\">Elektr</span><span style=\"color: #464646;\">i</span><span style=\"font-weight: bold; color: #464646;\">k, Doğalgaz ve Benzer</span><span style=\"color: #464646;\">i </span><span style=\"font-weight: bold; color: #464646;\">Isınma G</span><span style=\"color: #464646;\">i</span><span style=\"font-weight: bold; color: #464646;\">derler</span><span style=\"color: #464646;\">i </span><span style=\"font-weight: bold; color: #464646;\">Karşılığı Olarak Çalışanlara</span></p>\n\n<p class=\"p_Normal\" style=\"background: #ffffff;\"><span style=\"font-weight: bold; color: #464646;\">Yapılan Ödemelerde Gel</span><span style=\"color: #464646;\">i</span><span style=\"font-weight: bold; color: #464646;\">r Verg</span><span style=\"color: #464646;\">i</span><span style=\"font-weight: bold; color: #464646;\">s</span><span style=\"color: #464646;\">i </span><span style=\"font-weight: bold; color: #464646;\">İst</span><span style=\"color: #464646;\">i</span><span style=\"font-weight: bold; color: #464646;\">snası</span></p>\n\n<p class=\"p_Normal\" style=\"background: #ffffff;\"><span style=\"font-weight: bold; color: #464646;\">&nbsp;</span></p>\n\n<p class=\"p_Normal\" style=\"background: #ffffff;\"><span style=\"font-weight: bold; color: #464646;\">Yasal düzenleme</span></p>\n\n<p class=\"p_Normal\" style=\"background: #ffffff;\"><span style=\"font-weight: bold; color: #464646;\">MADDE 7- </span><span style=\"color: #464646;\">(1) 7420 sayılı Kanunun geçici1 inci maddesinde,</span></p>\n\n<p class=\"p_Normal\" style=\"background: #ffffff;\"><span style=\"color: #464646;\">“(1) Bu maddenin yürürlüğe girdiği tarihten itibaren işverenler tarafından çalışanlara elektrik, doğalgaz ve diğer ısınma giderlerine karşılık olmak üzere 30/6/2023 tarihine kadar (bu tarih dâhil) mevcut ücretlerine/prime esas kazançlarına ilave olarak yapılan aylık 1.000 Türk lirasını aşmayan ödemeler, 31/5/2006 tarihlive 5510 sayılı Sosyal Sigortalar ve Genel Sağlık Sigortası Kanununa göre prime esas kazanca dâhil edilmez ve bu tutar üzerinden 31/12/1960 tarihli ve 193 sayılı Gelir Vergisi Kanunu uyarınca gelir vergisi hesaplanmaz.</span></p>\n\n<p class=\"p_Normal\" style=\"background: #ffffff;\"><span style=\"color: #464646;\">(2) Bu maddenin uygulanmasına ilişkin usul ve esasları belirlemeye ilgisine göre Hazine ve Maliye Bakanlığı ve Çalışma ve Sosyal Güvenlik Bakanlığı yetkilidir.”</span></p>\n\n<p class=\"p_Normal\" style=\"background: #ffffff;\"><span style=\"color: #464646;\">hükmü yer almaktadır.</span></p>\n\n<p class=\"p_Normal\" style=\"background: #ffffff;\"><span style=\"font-weight: bold; color: #464646;\">&nbsp;</span></p>\n\n<p class=\"p_Normal\" style=\"background: #ffffff;\"><span style=\"font-weight: bold; color: #464646;\">İstisnanın kapsamı ve şartları</span></p>\n\n<p class=\"p_Normal\" style=\"background: #ffffff;\"><span style=\"font-weight: bold; color: #464646;\">MADDE 8- </span><span style=\"color: #464646;\">(1) 193 sayılı Kanunun 61 inci maddesinde, ücret, işverene tabi ve belirli bir işyerine bağlı olarak çalışanlara hizmet karşılığı verilen para ve ayınlar ile sağlanan ve parayla temsil edilebilen menfaatler olarak tanımlanmış olup ücretin; ödenek, tazminat, kasa tazminatı (mali sorumluluk tazminatı), tahsisat, zam, avans, aidat, huzur hakkı, prim, ikramiye, gider karşılığı veya başka adlar altında ödenmiş olması veya bir ortaklık münasebeti niteliğinde olmamak şartı ile kazancın belli bir yüzdesi şeklinde tayin edilmiş bulunmasının onun mahiyetini değiştirmeyeceği &nbsp;belirtilmiştir. Dolayısıyla hizmet erbabına ödenen aylık ücret, mesai, prim, ikramiye, gider karşılığı ve sair adlarla yapılan tüm ödemeler ve sağlanan menfaatler de ücret kapsamında değerlendirilmektedir.</span></p>\n\n<p class=\"p_Normal\" style=\"background: #ffffff;\"><span style=\"color: #464646;\">(2) İşverenler tarafından maddenin yürürlüğe girdiği 9/11/2022 tarihinden 30/6/2023 tarihine kadar (bu tarih dahil) çalışanlara mevcut ücretlerine ilave olarak elektrik, doğalgaz ve diğer ısınma giderlerine karşılık olmak üzere toplam aylık tutarı 1.000 Türk lirasını aşmayan ödemeler gelir vergisinden istisna edilmiştir.</span></p>\n\n<p class=\"p_Normal\" style=\"background: #ffffff;\"><span style=\"color: #464646;\">(3) İşverenler tarafından hizmet erbabına bu şekilde yapılan ödemelerin istisna kapsamında değerlendirilebilmesi için söz konusu ödemelerin;</span></p>\n\n<p class=\"p_Normal\" style=\"background: #ffffff;\"><span style=\"color: #464646;\"> &nbsp; &nbsp; &nbsp; &nbsp; &nbsp; &nbsp;a) 9/11/2022 tarihi ila 30/6/2023 tarihi (bu tarih dahil) arasında yapılması,</span></p>\n\n<p class=\"p_Normal\" style=\"background: #ffffff;\"><span style=\"color: #464646;\"> &nbsp; &nbsp; &nbsp; &nbsp; &nbsp; &nbsp;b) Elektrik, doğalgaz ve diğer ısınma giderlerine karşılık olmak üzere yapılması,</span></p>\n\n<p class=\"p_Normal\" style=\"background: #ffffff;\"><span style=\"color: #464646;\"> &nbsp; &nbsp; &nbsp; &nbsp; &nbsp; &nbsp;c) Aylık 1.000 Türk lirasını aşmaması,</span></p>\n\n<p class=\"p_Normal\" style=\"background: #ffffff;\"><span style=\"color: #464646;\"> &nbsp; &nbsp; &nbsp; &nbsp; &nbsp; &nbsp;d) Mevcut ücretlerine ilave olarak yapılması gerekmektedir</span></p>\n\n<p class=\"p_Normal\" style=\"background: #ffffff;\"><span style=\"color: #464646;\">&nbsp;</span></p>\n\n<p class=\"p_Normal\" style=\"background: #ffffff;\"><span style=\"color: #464646;\">şarttır</span></p>\n\n<p class=\"p_Normal\" style=\"background: #ffffff;\"><span style=\"color: #464646;\">…</span></p>\n\n<p class=\"p_Normal\" style=\"background: #ffffff;\"><span style=\"color: #464646;\">(9) Bu kapsamda yapılan ödemelere ilişkin olarak damga vergisi istisnası bulunmamaktadır.</span></p>\n\n<p class=\"p_Normal\" style=\"background: #ffffff;\"><span style=\"color: #464646;\">……….</span></p>\n\n<hr style=\"height:1px; color:#000000; border-width:0; background-color:#000000;\" /><p class=\"p_Normal\" style=\"text-align: center; background: #ffffff;\"><span style=\"font-weight: bold; color: #464646;\">GELİR VERGİSİ GENEL TEBLİĞİ</span></p>\n\n<p class=\"p_Normal\" style=\"text-align: center; background: #ffffff;\"><span style=\"font-weight: bold; color: #464646;\">(SERİ NO: 323.)</span></p>\n\n<p class=\"p_Normal\" style=\"text-align: center; background: #ffffff;\"><span style=\"background-color: #ffffff;\">&nbsp;</span></p>\n\n<p class=\"p_Normal\" style=\"background: #ffffff;\"><span style=\"font-weight: bold; color: #464646;\">BİRİNCİ BÖLÜM</span></p>\n\n<p class=\"p_Normal\" style=\"background: #ffffff;\"><span style=\"font-weight: bold; color: #464646;\">Amaç ve Yasal Düzenlemeler</span></p>\n\n<p class=\"p_Normal\" style=\"background: #ffffff;\"><span style=\"font-weight: bold; color: #464646;\">Amaç</span></p>\n\n<p class=\"p_Normal\" style=\"background: #ffffff;\"><span style=\"font-weight: bold; color: #464646;\">MADDE 1 – </span><span style=\"color: #464646;\">(1) Bu Tebliğin amacı, 31/12/1960 tarihli ve 193 sayılı Gelir Vergisi Kanununun 9/10, 21, 23/8, 23/10, 31, 40/1, 40/7, 47, 48, 68 mükerrer 80, 82, 86, 103 ve mükerrer 121 inci maddelerinde yer alan ve yeniden değerleme oranında artırılan maktu had ve tutarlar, basit usule tabi mükelleflerde toplu belge düzenleme uygulaması ile 1/1/2006 tarihinden önce ihraç edilen bir kısım menkul kıymetlerden 2022 takvim yılında elde edilen menkul sermaye iradının beyanında dikkate alınacak indirim oranı uygulamasına ilişkin hususların açıklanmasıdır.</span></p>\n\n<p class=\"p_Normal\" style=\"background: #ffffff;\"><span style=\"color: #464646;\">&nbsp;</span></p>\n\n<p class=\"p_Normal\" style=\"background: #ffffff;\"><span style=\"font-weight: bold; color: #464646;\">Yasal düzenlemeler</span></p>\n\n<p class=\"p_Normal\" style=\"background: #ffffff;\"><span style=\"font-weight: bold; color: #464646;\">MADDE 2 – </span><span style=\"color: #464646;\">(1) 193 sayılı Kanunun mükerrer 121 inci maddesinde:</span></p>\n\n<p class=\"p_Normal\" style=\"background: #ffffff;\"><span style=\"color: #464646;\">“…</span></p>\n\n<p class=\"p_Normal\" style=\"background: #ffffff;\"><span style=\"color: #464646;\">Birinci fıkrada yer alan tutar, her yıl bir önceki yıla ilişkin olarak 213 sayılı Vergi Usul Kanunu hükümlerine göre belirlenen yeniden değerleme oranında artırılmak suretiyle uygulanır. Bu şekilde hesaplanan tutarın % 5'ini aşmayan kesirler dikkate alınmaz. Cumhurbaşkanı, birinci fıkrada yer alan oranı ve tutarı iki katına kadar artırmaya, sıfıra kadar indirmeye, kanuni oran ve tutarına getirmeye; Maliye Bakanlığı, maddenin uygulanmasına ilişkin usul ve esasları belirlemeye yetkilidir.”</span></p>\n\n<p class=\"p_Normal\" style=\"background: #ffffff;\"><span style=\"color: #464646;\">hükmü yer almaktadır.</span></p>\n\n<p class=\"p_Normal\" style=\"background: #ffffff;\"><span style=\"color: #464646;\">(2) 193 sayılı Kanunun mükerrer 123 üncü maddesinde:</span></p>\n\n<p class=\"p_Normal\" style=\"background: #ffffff;\"><span style=\"color: #464646;\">“…</span></p>\n\n<p style=\"text-indent: 0; padding-left: 20px; margin: 0 0 0 20px;\"><span class=\"f_Normal\" style=\"color:#464646;display:inline-block;width:20px;margin-left:-20px\">2.</span><span style=\"color: #464646;\">Bu Kanunun 9/10, 19, 21, 23/8, 23/10, 31, 40/1, 40/7, 47, 48, 68 mükerrer 80, 82 ve 86 ncı maddeleri ile 89 uncu maddesinin birinci fıkrasının (15) numaralı bendinde yer alan maktu had ve tutarlar, her yıl bir önceki yıla ilişkin olarak Vergi Usul Kanunu hükümlerine göre belirlenen yeniden değerleme oranında artırılmak suretiyle uygulanır. Bu şekilde hesaplanan maktu had ve tutarların % 5'ini aşmayan kesirler dikkate alınmaz. Cumhurbaşkanı, bu surette tespit edilen had ve tutarları % 50'sine kadar artırmaya veya indirmeye yetkilidir.</span></p><p style=\"text-indent: 0; padding-left: 20px; margin: 0 0 0 20px;\"><span class=\"f_Normal\" style=\"color:#464646;display:inline-block;width:20px;margin-left:-20px\">3.</span><span style=\"color: #464646;\">Bu Kanunun 103 üncü maddesinde yer alan vergi tarifesinin gelir dilim tutarları hakkında, bu maddenin (2) numaralı fıkrası uygulanır.”</span></p><p class=\"p_Normal\" style=\"background: #ffffff;\"><span style=\"color: #464646;\">hükmü yer almaktadır.</span></p>\n\n<p class=\"p_Normal\" style=\"background: #ffffff;\"><span style=\"color: #464646;\">&nbsp;</span></p>\n\n<p class=\"p_Normal\" style=\"background: #ffffff;\"><span style=\"font-weight: bold; color: #464646;\">İKİNCİ BÖLÜM</span></p>\n\n<p class=\"p_Normal\" style=\"background: #ffffff;\"><span style=\"font-weight: bold; color: #464646;\">Yeniden Değerleme Oranında Artırılan Had ve Tutarlar</span></p>\n\n<p class=\"p_Normal\" style=\"background: #ffffff;\"><span style=\"font-weight: bold; color: #464646;\">&nbsp;</span></p>\n\n<p class=\"p_Normal\" style=\"background: #ffffff;\"><span style=\"font-weight: bold; color: #464646;\"> Yeniden değerleme oranında artırılan had ve tutarlar</span></p>\n\n<p class=\"p_Normal\" style=\"background: #ffffff;\"><span style=\"font-weight: bold; color: #464646;\">MADDE 3 – </span><span style=\"color: #464646;\">(1) 193 sayılı Kanunun mükerrer 123 üncü maddesi hükmü uyarınca, aynı Kanunun 9/10, 21, 23/8, 23/10, 31, 40/1, 40/7, 47, 48, 68 mükerrer 80, 82, 86, ve 103 üncü maddelerinde yer alan ve 2022 yılında uygulanan had ve tutarlar 24/11/2022 tarihli ve 32023 sayılı Resmî Gazete’de yayımlanan Vergi Usul Kanunu Genel Tebliği (Sıra No:542) ile 2022 yılı için % 122,93 (yüz yirmi iki virgül doksan üç) olarak tespit edilen yeniden değerleme oranında artırılması suretiyle belirlenerek, 2023 takvim yılında uygulanacak olan had ve tutarlar aşağıdaki şekilde tespit edilmiştir.</span></p>\n\n<p class=\"p_Normal\" style=\"background: #ffffff;\"><span style=\"font-weight: bold; color: #464646; text-decoration: underline;\">Yemek bedelinde istisna tutarı</span></p>\n\n<p class=\"p_Normal\" style=\"background: #ffffff;\"><span style=\"color: #464646;\">İşyerinde veya müştemilatında yemek verilmeyen durumlarda çalışılan günlere ait bir günlük yemek bedeline ilişkin istisna tutarı 110 TL</span></p>\n\n<p class=\"p_Normal\" style=\"background: #ffffff;\"><span style=\"color: #464646;\">İşverenler tarafından hizmet erbabına işyerinde veya müştemilatında yemek verilmeyen durumlarda, yemek bedelinin nakit olarak verilmesi suretiyle sağlanan menfaatler de istisna kapsamına alınmıştır.</span></p>\n\n<p class=\"p_Normal\" style=\"background: #ffffff;\"><span style=\"font-weight: bold; color: #464646;\">Hizmet erbabına nakit olarak ödenen yemek bedelinin gelir vergisinden istisna edilebilmesi için;</span></p>\n\n<p class=\"p_Normal\" style=\"background: #ffffff;\"><span style=\"font-weight: bold; color: #464646;\"> &nbsp; &nbsp; &nbsp; &nbsp; &nbsp; a) İşverenler tarafından işyerinde veya müştemilatında yemek verilmemesi,</span></p>\n\n<p class=\"p_Normal\" style=\"background: #ffffff;\"><span style=\"font-weight: bold; color: #464646;\"> &nbsp; &nbsp; &nbsp; &nbsp; &nbsp; b) Günlük yemek bedelinin 110 Türk lirasını aşmaması,</span></p>\n\n<p class=\"p_Normal\" style=\"background: #ffffff;\"><span style=\"font-weight: bold; color: #464646;\"> &nbsp; &nbsp; &nbsp; &nbsp; &nbsp; c) Fiilen çalışılan günlere ilişkin olması,</span></p>\n\n<p class=\"p_Normal\" style=\"background: #ffffff;\"><span style=\"font-weight: bold; color: #464646;\">gerekmektedir.</span></p>\n\n<p class=\"p_Normal\" style=\"background: #ffffff;\"><span style=\"color: #464646;\">Nakit olarak yapılan yemek bedeli ödemelerinin, 18/11/2008 tarihli ve 27058 sayılı Resmî Gazete’de yayımlanan Ücret, Prim, İkramiye ve Bu Nitelikteki Her Türlü İstihkakın Bankalar Aracılığıyla Ödenmesine Dair Yönetmelikte belirlenen ödeme usulüne göre yapılması gerekmektedir.</span></p>\n\n<p class=\"p_Normal\" style=\"background: #ffffff;\"><span style=\"color: #464646;\">İşverenler tarafından hizmet erbabına yapılan ödemelere ilişkin olarak düzenlenen kağıtlarda yer alan tutarın, 193 sayılı Kanunun 23 üncü maddesinin birinci fıkrasının (19) numaralı bendinde yer alan istisnaya isabet eden kısmı damga vergisinden istisnadır.</span></p>\n\n<p class=\"p_Normal\" style=\"background: #ffffff;\"><span style=\"font-weight: bold; color: #464646; text-decoration: underline;\">&nbsp;</span></p>\n\n<p class=\"p_Normal\" style=\"background: #ffffff;\"><span style=\"font-weight: bold; color: #464646; text-decoration: underline;\">Ulaşım gideri istisna tutarı</span></p>\n\n<p class=\"p_Normal\" style=\"background: #ffffff;\"><span style=\"color: #464646;\">193 sayılı Kanun 23 üncü maddesinin birinci fıkrasının (10) numaralı bendinde yer alan işverenlerce hizmet erbabının işyerine gidip gelmesi için sağlanan menfaatlere ilişkin istisna tutarı 56 TL</span></p>\n\n<p class=\"p_Normal\" style=\"background: #ffffff;\"><span style=\"color: #464646;\">&nbsp;</span></p>\n\n<p class=\"p_Normal\" style=\"background: #ffffff;\"><span style=\"font-weight: bold; color: #464646;\">Engellilik indirim tutarları</span></p>\n\n<p class=\"p_Normal\" style=\"background: #ffffff;\"><span style=\"color: #464646;\">193 sayılı Kanunun 31 inci maddesinin ikinci fıkrasında yer alan engellilik indirimi tutarları;</span></p>\n\n<p class=\"p_Normal\" style=\"background: #ffffff;\"><span style=\"color: #464646;\">- Birinci derece engelliler için &nbsp; &nbsp; &nbsp; &nbsp; &nbsp; &nbsp; 4.400. TL,</span></p>\n\n<p class=\"p_Normal\" style=\"background: #ffffff;\"><span style=\"color: #464646;\">- İkinci derece engelliler için &nbsp; &nbsp; &nbsp; &nbsp; &nbsp; &nbsp; 2.600 TL,</span></p>\n\n<p class=\"p_Normal\" style=\"background: #ffffff;\"><span style=\"color: #464646;\">- Üçüncü derece engelliler için &nbsp; &nbsp; &nbsp; &nbsp; &nbsp;1.100 TL,</span></p>\n\n<p class=\"p_Normal\" style=\"background: #ffffff;\"><span style=\"color: #464646;\">…….</span></p>\n\n<p class=\"p_Normal\" style=\"background: #ffffff;\"><span style=\"color: #464646;\"> &nbsp; &nbsp; &nbsp; &nbsp; &nbsp; &nbsp; &nbsp; </span></p>\n\n<p class=\"p_Normal\" style=\"background: #ffffff;\"><span style=\"color: #464646;\">&nbsp;</span></p>\n\n<p class=\"p_Normal\" style=\"background: #ffffff;\"><span style=\"font-weight: bold; color: #464646;\">Demirbaşa kaydedilmek üzere otomobil alımında amortisman ve gider uygulama sınırı</span></p>\n\n<p class=\"p_Normal\" style=\"background: #ffffff;\"><span style=\"color: #464646;\">193 sayılı Gelir Vergisi Kanunun mesleki giderlere dair 68 inci maddesinin birinci fıkrasının;</span></p>\n\n<p class=\"p_Normal\" style=\"background: #ffffff;\"><span style=\"color: #464646;\">- 4 numaralı bendinde araç amortismanı olarak indirim konusu yapılabilecek tutar; özel tüketim vergisi ve katma değer vergisi hariç 500.000 TL, vergilerin maliyet bedeline eklendiği veya binek otomobilin ikinci el olarak iktisap edildiği hallerde 950.000 TL,</span></p>\n\n<p class=\"p_Normal\" style=\"background: #ffffff;\"><span style=\"color: #464646;\">- 5 numaralı bendinde gider olarak indirim konusu yapılabilecek aylık araç kiralama bedeli 17.000 TL, indirim konusu yapılabilecek özel tüketim vergisi ve katma değer vergisinin toplam tutarı 440.000 TL,</span></p>\n\n<p class=\"p_Normal\" style=\"background: #ffffff;\"><span style=\"color: #464646;\">olarak tespit edilmiştir.</span></p>\n\n<p class=\"p_Normal\" style=\"background: #ffffff;\"><span style=\"color: #464646;\">&nbsp;</span></p>\n\n<p class=\"p_Normal\" style=\"background: #ffffff;\"><span style=\"font-weight: bold; color: #464646;\">2023 yılı gelirlerinin vergilendirilmesinde vergi matrah dilim ve nispetleri</span></p>\n\n<p class=\"p_Normal\" style=\"background: #ffffff;\"><span style=\"color: #464646;\">193 sayılı Kanunun 103 üncü maddesinin birinci fıkrasında yer alan gelir vergisine tabi gelirlerin vergilendirilmesinde esas alınan tarife, 2023 takvim yılı gelirlerinin vergilendirilmesinde esas alınmak üzere aşağıdaki şekilde yeniden belirlenmiştir.</span></p>\n\n<p class=\"p_Normal\" style=\"background: #ffffff;\"><span style=\"color: #464646;\">&nbsp;</span></p>\n\n<p class=\"p_Normal\" style=\"background: #ffffff;\"><span style=\"color: #464646;\">70.000 TL'ye kadar &nbsp; &nbsp; &nbsp; &nbsp; &nbsp; &nbsp; &nbsp; &nbsp; &nbsp; &nbsp; &nbsp; &nbsp; &nbsp; &nbsp; &nbsp; &nbsp; &nbsp; &nbsp; &nbsp; &nbsp; &nbsp; &nbsp; &nbsp; &nbsp; &nbsp; &nbsp; &nbsp; &nbsp; &nbsp; &nbsp; &nbsp; &nbsp; &nbsp; &nbsp; &nbsp; &nbsp; &nbsp; &nbsp; &nbsp; &nbsp; &nbsp; &nbsp; &nbsp; &nbsp; &nbsp; &nbsp; &nbsp; &nbsp; &nbsp; % 15</span></p>\n\n<p class=\"p_Normal\" style=\"background: #ffffff;\"><span style=\"color: #464646;\">150.000 TL'nin 70.000 TL'si için 10.500 TL, fazlası &nbsp; &nbsp; &nbsp; &nbsp; &nbsp; &nbsp; &nbsp; &nbsp; &nbsp; &nbsp; &nbsp; &nbsp; &nbsp; &nbsp; &nbsp; &nbsp; &nbsp; &nbsp; &nbsp; &nbsp; &nbsp; &nbsp; &nbsp; &nbsp; &nbsp; &nbsp; &nbsp; % 20</span></p>\n\n<p class=\"p_Normal\" style=\"background: #ffffff;\"><span style=\"color: #464646;\">370.000 TL'nin 150.000 TL'si için 26.500 TL, (ücret gelirlerinde 550.000 TL'nin</span></p>\n\n<p class=\"p_Normal\" style=\"background: #ffffff;\"><span style=\"color: #464646;\"> &nbsp; &nbsp; &nbsp; &nbsp; &nbsp;150.000 TL'si için 26.500 TL), fazlası &nbsp; &nbsp; &nbsp; &nbsp; &nbsp; &nbsp; &nbsp; &nbsp; &nbsp; &nbsp; &nbsp; &nbsp; &nbsp; &nbsp; &nbsp; &nbsp; &nbsp; &nbsp; &nbsp; &nbsp; &nbsp; &nbsp; &nbsp; &nbsp; &nbsp; &nbsp; &nbsp; &nbsp; &nbsp; &nbsp; &nbsp; &nbsp;% 27</span></p>\n\n<p class=\"p_Normal\" style=\"background: #ffffff;\"><span style=\"color: #464646;\">1.900.000 TL'nin 370.000 TL'si için 85.900 TL, (ücret gelirlerinde</span></p>\n\n<p class=\"p_Normal\" style=\"background: #ffffff;\"><span style=\"color: #464646;\"> &nbsp; &nbsp; &nbsp; &nbsp; &nbsp; 1.900.000 TL'nin 550.000 TL'si için 134.500 TL), fazlası &nbsp; &nbsp; &nbsp; &nbsp; &nbsp; &nbsp; &nbsp; &nbsp; &nbsp; &nbsp; &nbsp; &nbsp; &nbsp; &nbsp; &nbsp; &nbsp; &nbsp; &nbsp;% 35</span></p>\n\n<p class=\"p_Normal\" style=\"background: #ffffff;\"><span style=\"color: #464646;\">1.900.000 TL’den fazlasının 1.900.000 TL’si için 621.400 TL (ücret gelirlerinde</span></p>\n\n<p class=\"p_Normal\" style=\"text-align: left; background: #ffffff;\"><span style=\"color: #464646;\"> &nbsp; &nbsp; &nbsp; &nbsp; &nbsp; 1.900.000 TL’den fazlasının 1.900.000 TL’si için 607.000TL), fazlası &nbsp; &nbsp; &nbsp; &nbsp; &nbsp; &nbsp; &nbsp; &nbsp; &nbsp; % 40</span></p>\n\n\n\n<!--ZOOMSTOP-->\n\n\n\n\n\n<!DOCTYPE html PUBLIC \"-//W3C//DTD XHTML 1.0 Transitional//EN\" \"http://www.w3.org/TR/xhtml1/DTD/xhtml1-transitional.dtd\">\n\n<html xmlns=\"http://www.w3.org/1999/xhtml\">\n\n\n\n<head>\n\n<meta http-equiv=\"Content-Type\" content=\"text/html; charset=utf-8\" />\n\n\n\n   <script type=\"text/javascript\" src=\"hmpopup_html.js\"></script>\n\n\n\n   <script type=\"text/javascript\">\n\n     HMSyncTOC(\"index.html\", \"2022-495-sayili-genelyazi.html\");\n\n   </script>\n\n</head>\n\n<body>\n\n<!-- Google tag (gtag.js) -->\n\n<script async src=\"https://www.googletagmanager.com/gtag/js?id=G-L1LQTG9GMG\"></script>\n\n<script>\n\n  window.dataLayer = window.dataLayer || [];\n\n  function gtag(){dataLayer.push(arguments);}\n\n  gtag('js', new Date());\n\n\n\n  gtag('config', 'G-L1LQTG9GMG');\n\n</script>\n\n\n\n<hr>\n\n<div class=\"topicfooter\"><p class=\"topicfooter\"> <a href=\"hangi-konular-guncellendi.html\" target=\"hmcontent\">Güncelleme: 07.01.2023</a></p>\n\n</div>\n\n\n\n<div class=\"topicfooter\">\n\n<p class=\"topicfooter\"> <a href=\"fihrist.html\" target=\"hmcontent\">© Noterlik Rehberi (Sait Doğan - Sakarya 5. Noteri)</a></p>\n\n</div>\n\n\n\n</div> <!-- idcontent -->\n\n</div><!-- hmbox --> \n\n</body>\n\n</html>\n\n",
  "conversion_date": "2025-10-16T01:16:44.929604"
}